{
"meta":{"test_sets":[],"test_metrics":[],"learn_metrics":[{"best_value":"Min","name":"RMSE"}],"launch_mode":"Train","parameters":"","iteration_count":1000,"learn_sets":["learn"],"name":"experiment"},
"iterations":[
{"learn":[14.61268541],"iteration":0,"passed_time":0.1682448751,"remaining_time":168.0766302},
{"learn":[14.23196558],"iteration":1,"passed_time":0.1700672047,"remaining_time":84.86353514},
{"learn":[13.86674177],"iteration":2,"passed_time":0.1715258775,"remaining_time":57.00376663},
{"learn":[13.49946468],"iteration":3,"passed_time":0.1731702965,"remaining_time":43.11940384},
{"learn":[13.16661202],"iteration":4,"passed_time":0.1746507772,"remaining_time":34.75550466},
{"learn":[12.85632158],"iteration":5,"passed_time":0.1759079041,"remaining_time":29.14207611},
{"learn":[12.56784336],"iteration":6,"passed_time":0.1771637874,"remaining_time":25.13194869},
{"learn":[12.31617801],"iteration":7,"passed_time":0.1786452236,"remaining_time":22.15200773},
{"learn":[12.01509946],"iteration":8,"passed_time":0.1796517784,"remaining_time":19.78165694},
{"learn":[11.71512571],"iteration":9,"passed_time":0.180542625,"remaining_time":17.87371987},
{"learn":[11.43264457],"iteration":10,"passed_time":0.1813472795,"remaining_time":16.30476904},
{"learn":[11.17973129],"iteration":11,"passed_time":0.1823782198,"remaining_time":15.01580676},
{"learn":[10.93746433],"iteration":12,"passed_time":0.1832941239,"remaining_time":13.91625387},
{"learn":[10.69387075],"iteration":13,"passed_time":0.1842168774,"remaining_time":12.97413151},
{"learn":[10.4615922],"iteration":14,"passed_time":0.1850600691,"remaining_time":12.15227787},
{"learn":[10.2299235],"iteration":15,"passed_time":0.1858720964,"remaining_time":11.43113393},
{"learn":[10.01419731],"iteration":16,"passed_time":0.186504836,"remaining_time":10.78436787},
{"learn":[9.795856918],"iteration":17,"passed_time":0.187416754,"remaining_time":10.22462513},
{"learn":[9.60040151],"iteration":18,"passed_time":0.1895156892,"remaining_time":9.784994269},
{"learn":[9.418664989],"iteration":19,"passed_time":0.1905682036,"remaining_time":9.337841975},
{"learn":[9.249278645],"iteration":20,"passed_time":0.1912242525,"remaining_time":8.914692531},
{"learn":[9.090113396],"iteration":21,"passed_time":0.1918778174,"remaining_time":8.529841154},
{"learn":[8.909548708],"iteration":22,"passed_time":0.1926679622,"remaining_time":8.184199961},
{"learn":[8.740140208],"iteration":23,"passed_time":0.1933611819,"remaining_time":7.863354731},
{"learn":[8.59377682],"iteration":24,"passed_time":0.1940290626,"remaining_time":7.56713344},
{"learn":[8.453885414],"iteration":25,"passed_time":0.1948204063,"remaining_time":7.298272144},
{"learn":[8.317732234],"iteration":26,"passed_time":0.1956213846,"remaining_time":7.049615083},
{"learn":[8.180896085],"iteration":27,"passed_time":0.1964245332,"remaining_time":6.818737367},
{"learn":[8.053220863],"iteration":28,"passed_time":0.197139678,"remaining_time":6.600780253},
{"learn":[7.924234474],"iteration":29,"passed_time":0.1978363982,"remaining_time":6.396710208},
{"learn":[7.818879511],"iteration":30,"passed_time":0.1985675557,"remaining_time":6.206837467},
{"learn":[7.719346395],"iteration":31,"passed_time":0.1992137421,"remaining_time":6.026215698},
{"learn":[7.624163594],"iteration":32,"passed_time":0.1998282913,"remaining_time":5.855574475},
{"learn":[7.524952543],"iteration":33,"passed_time":0.2005609249,"remaining_time":5.698289809},
{"learn":[7.424464745],"iteration":34,"passed_time":0.2012707404,"remaining_time":5.549321843},
{"learn":[7.327482321],"iteration":35,"passed_time":0.2021004045,"remaining_time":5.411799721},
{"learn":[7.238666841],"iteration":36,"passed_time":0.2028472922,"remaining_time":5.279511956},
{"learn":[7.158842395],"iteration":37,"passed_time":0.203690551,"remaining_time":5.156587106},
{"learn":[7.074348246],"iteration":38,"passed_time":0.2044574943,"remaining_time":5.03804236},
{"learn":[6.992269093],"iteration":39,"passed_time":0.2053490188,"remaining_time":4.928376452},
{"learn":[6.925219745],"iteration":40,"passed_time":0.2061423986,"remaining_time":4.821720981},
{"learn":[6.86013671],"iteration":41,"passed_time":0.2069790144,"remaining_time":4.721092756},
{"learn":[6.786739622],"iteration":42,"passed_time":0.2077123285,"remaining_time":4.622806938},
{"learn":[6.73057926],"iteration":43,"passed_time":0.2083827457,"remaining_time":4.527588748},
{"learn":[6.666356486],"iteration":44,"passed_time":0.2090503019,"remaining_time":4.436511963},
{"learn":[6.606182832],"iteration":45,"passed_time":0.2097264774,"remaining_time":4.34954477},
{"learn":[6.547854615],"iteration":46,"passed_time":0.2104217144,"remaining_time":4.266636039},
{"learn":[6.49240675],"iteration":47,"passed_time":0.2110713818,"remaining_time":4.186249073},
{"learn":[6.431317261],"iteration":48,"passed_time":0.2117320953,"remaining_time":4.109331074},
{"learn":[6.377586395],"iteration":49,"passed_time":0.2123876452,"remaining_time":4.035365259},
{"learn":[6.327558015],"iteration":50,"passed_time":0.2130717177,"remaining_time":3.964805099},
{"learn":[6.282040317],"iteration":51,"passed_time":0.2137580026,"remaining_time":3.896972817},
{"learn":[6.237655841],"iteration":52,"passed_time":0.214844336,"remaining_time":3.838822381},
{"learn":[6.192792003],"iteration":53,"passed_time":0.2156889271,"remaining_time":3.778550464},
{"learn":[6.150579347],"iteration":54,"passed_time":0.2175337334,"remaining_time":3.737625055},
{"learn":[6.115693845],"iteration":55,"passed_time":0.2187759905,"remaining_time":3.687938125},
{"learn":[6.078780782],"iteration":56,"passed_time":0.2198243491,"remaining_time":3.636743179},
{"learn":[6.045146957],"iteration":57,"passed_time":0.2207765314,"remaining_time":3.58571539},
{"learn":[6.008080327],"iteration":58,"passed_time":0.2216888982,"remaining_time":3.535750055},
{"learn":[5.977575734],"iteration":59,"passed_time":0.2225580169,"remaining_time":3.486742265},
{"learn":[5.948036502],"iteration":60,"passed_time":0.2233479504,"remaining_time":3.43809386},
{"learn":[5.914888282],"iteration":61,"passed_time":0.2241426612,"remaining_time":3.391061552},
{"learn":[5.884957796],"iteration":62,"passed_time":0.2249077543,"remaining_time":3.345056599},
{"learn":[5.849539885],"iteration":63,"passed_time":0.2256588233,"remaining_time":3.300260291},
{"learn":[5.821387627],"iteration":64,"passed_time":0.2263610054,"remaining_time":3.256116},
{"learn":[5.797012279],"iteration":65,"passed_time":0.2272031883,"remaining_time":3.215269362},
{"learn":[5.768685095],"iteration":66,"passed_time":0.2281547557,"remaining_time":3.177140105},
{"learn":[5.755484587],"iteration":67,"passed_time":0.2286895457,"remaining_time":3.134392009},
{"learn":[5.731887055],"iteration":68,"passed_time":0.2298088789,"remaining_time":3.100754583},
{"learn":[5.707148487],"iteration":69,"passed_time":0.2306649541,"remaining_time":3.064548676},
{"learn":[5.685365039],"iteration":70,"passed_time":0.2315996438,"remaining_time":3.03036717},
{"learn":[5.663541834],"iteration":71,"passed_time":0.2325680585,"remaining_time":2.997543865},
{"learn":[5.638108797],"iteration":72,"passed_time":0.2335100911,"remaining_time":2.96525828},
{"learn":[5.619204893],"iteration":73,"passed_time":0.234334491,"remaining_time":2.93234782},
{"learn":[5.598472793],"iteration":74,"passed_time":0.2350610908,"remaining_time":2.899086787},
{"learn":[5.577007075],"iteration":75,"passed_time":0.2357742945,"remaining_time":2.866519055},
{"learn":[5.562637084],"iteration":76,"passed_time":0.236458287,"remaining_time":2.834428557},
{"learn":[5.54729991],"iteration":77,"passed_time":0.2371667627,"remaining_time":2.803432759},
{"learn":[5.530737623],"iteration":78,"passed_time":0.2379376305,"remaining_time":2.77393111},
{"learn":[5.513704873],"iteration":79,"passed_time":0.2387368733,"remaining_time":2.745474043},
{"learn":[5.501575529],"iteration":80,"passed_time":0.2395831937,"remaining_time":2.718234013},
{"learn":[5.484080734],"iteration":81,"passed_time":0.2404621592,"remaining_time":2.692003197},
{"learn":[5.472178894],"iteration":82,"passed_time":0.2414012976,"remaining_time":2.667048071},
{"learn":[5.458923342],"iteration":83,"passed_time":0.2421501785,"remaining_time":2.640590042},
{"learn":[5.451382371],"iteration":84,"passed_time":0.2426859412,"remaining_time":2.612442779},
{"learn":[5.441410748],"iteration":85,"passed_time":0.2434797627,"remaining_time":2.587680268},
{"learn":[5.434047468],"iteration":86,"passed_time":0.2440654678,"remaining_time":2.561284737},
{"learn":[5.422107497],"iteration":87,"passed_time":0.2451026287,"remaining_time":2.540154516},
{"learn":[5.40731265],"iteration":88,"passed_time":0.2460587028,"remaining_time":2.518645823},
{"learn":[5.396360181],"iteration":89,"passed_time":0.2469999277,"remaining_time":2.497443713},
{"learn":[5.383793239],"iteration":90,"passed_time":0.2479264755,"remaining_time":2.476540289},
{"learn":[5.369605034],"iteration":91,"passed_time":0.2488017018,"remaining_time":2.455564622},
{"learn":[5.357467333],"iteration":92,"passed_time":0.2496417646,"remaining_time":2.434678285},
{"learn":[5.341109968],"iteration":93,"passed_time":0.2503825895,"remaining_time":2.413261979},
{"learn":[5.330529276],"iteration":94,"passed_time":0.2511990248,"remaining_time":2.393001236},
{"learn":[5.319862075],"iteration":95,"passed_time":0.2519325304,"remaining_time":2.372364661},
{"learn":[5.313052243],"iteration":96,"passed_time":0.2527717599,"remaining_time":2.353122672},
{"learn":[5.299677207],"iteration":97,"passed_time":0.2535922373,"remaining_time":2.334083654},
{"learn":[5.287546698],"iteration":98,"passed_time":0.2544968737,"remaining_time":2.316178619},
{"learn":[5.279803754],"iteration":99,"passed_time":0.2555230284,"remaining_time":2.299707256},
{"learn":[5.272254612],"iteration":100,"passed_time":0.256588135,"remaining_time":2.283888449},
{"learn":[5.268813888],"iteration":101,"passed_time":0.2570601749,"remaining_time":2.263137618},
{"learn":[5.258113767],"iteration":102,"passed_time":0.2579224343,"remaining_time":2.246178869},
{"learn":[5.251018576],"iteration":103,"passed_time":0.2587001659,"remaining_time":2.22880143},
{"learn":[5.24171237],"iteration":104,"passed_time":0.2596165156,"remaining_time":2.212921728},
{"learn":[5.233984943],"iteration":105,"passed_time":0.2604711627,"remaining_time":2.196803957},
{"learn":[5.226240449],"iteration":106,"passed_time":0.2613149474,"remaining_time":2.180880822},
{"learn":[5.220541644],"iteration":107,"passed_time":0.2622312378,"remaining_time":2.165835779},
{"learn":[5.211712096],"iteration":108,"passed_time":0.2632290382,"remaining_time":2.151716266},
{"learn":[5.203388597],"iteration":109,"passed_time":0.2641268447,"remaining_time":2.137026289},
{"learn":[5.196026544],"iteration":110,"passed_time":0.2650250101,"remaining_time":2.122587694},
{"learn":[5.188716772],"iteration":111,"passed_time":0.2659351349,"remaining_time":2.108485713},
{"learn":[5.182163132],"iteration":112,"passed_time":0.2669194604,"remaining_time":2.095199658},
{"learn":[5.17764747],"iteration":113,"passed_time":0.2677788505,"remaining_time":2.081158434},
{"learn":[5.170548056],"iteration":114,"passed_time":0.2685282221,"remaining_time":2.066499796},
{"learn":[5.165901827],"iteration":115,"passed_time":0.2692094529,"remaining_time":2.051561693},
{"learn":[5.160333668],"iteration":116,"passed_time":0.2700216704,"remaining_time":2.037855855},
{"learn":[5.148953243],"iteration":117,"passed_time":0.2708158781,"remaining_time":2.024233937},
{"learn":[5.144729126],"iteration":118,"passed_time":0.2714434435,"remaining_time":2.009593897},
{"learn":[5.139939946],"iteration":119,"passed_time":0.2723768191,"remaining_time":1.997430007},
{"learn":[5.132898872],"iteration":120,"passed_time":0.2732306519,"remaining_time":1.984873909},
{"learn":[5.129073077],"iteration":121,"passed_time":0.2743127948,"remaining_time":1.974152737},
{"learn":[5.127123916],"iteration":122,"passed_time":0.2751876668,"remaining_time":1.962110437},
{"learn":[5.121282057],"iteration":123,"passed_time":0.2764356688,"remaining_time":1.952884241},
{"learn":[5.114489821],"iteration":124,"passed_time":0.2775507153,"remaining_time":1.942855007},
{"learn":[5.107777291],"iteration":125,"passed_time":0.2783859051,"remaining_time":1.93102604},
{"learn":[5.103518754],"iteration":126,"passed_time":0.2794131484,"remaining_time":1.920690383},
{"learn":[5.101133351],"iteration":127,"passed_time":0.2800459072,"remaining_time":1.907812742},
{"learn":[5.096462705],"iteration":128,"passed_time":0.2810140492,"remaining_time":1.897389433},
{"learn":[5.08562082],"iteration":129,"passed_time":0.2818781813,"remaining_time":1.886415521},
{"learn":[5.080483682],"iteration":130,"passed_time":0.2827770475,"remaining_time":1.875826368},
{"learn":[5.07437499],"iteration":131,"passed_time":0.2836287287,"remaining_time":1.865073761},
{"learn":[5.070683732],"iteration":132,"passed_time":0.2845477231,"remaining_time":1.854908841},
{"learn":[5.06432037],"iteration":133,"passed_time":0.2855256994,"remaining_time":1.845263102},
{"learn":[5.057436484],"iteration":134,"passed_time":0.2864681518,"remaining_time":1.835518158},
{"learn":[5.053254656],"iteration":135,"passed_time":0.287304599,"remaining_time":1.825229217},
{"learn":[5.04801663],"iteration":136,"passed_time":0.2881437903,"remaining_time":1.815095555},
{"learn":[5.045680836],"iteration":137,"passed_time":0.2888896909,"remaining_time":1.804513866},
{"learn":[5.041857933],"iteration":138,"passed_time":0.290035203,"remaining_time":1.796548991},
{"learn":[5.035264888],"iteration":139,"passed_time":0.2910756709,"remaining_time":1.788036264},
{"learn":[5.028771948],"iteration":140,"passed_time":0.2921565487,"remaining_time":1.779875711},
{"learn":[5.024912247],"iteration":141,"passed_time":0.2931144349,"remaining_time":1.771071726},
{"learn":[5.02239068],"iteration":142,"passed_time":0.2940735068,"remaining_time":1.762384582},
{"learn":[5.017110572],"iteration":143,"passed_time":0.295062179,"remaining_time":1.753980731},
{"learn":[5.010707886],"iteration":144,"passed_time":0.2961795744,"remaining_time":1.74643818},
{"learn":[5.004389868],"iteration":145,"passed_time":0.2970298031,"remaining_time":1.737420903},
{"learn":[4.997628683],"iteration":146,"passed_time":0.2978473822,"remaining_time":1.728325286},
{"learn":[4.991497851],"iteration":147,"passed_time":0.2987679493,"remaining_time":1.719934411},
{"learn":[4.988345253],"iteration":148,"passed_time":0.299759253,"remaining_time":1.712047814},
{"learn":[4.98460423],"iteration":149,"passed_time":0.3007824235,"remaining_time":1.704433733},
{"learn":[4.982441783],"iteration":150,"passed_time":0.301788091,"remaining_time":1.696808538},
{"learn":[4.977461771],"iteration":151,"passed_time":0.3027846043,"remaining_time":1.689219371},
{"learn":[4.973601586],"iteration":152,"passed_time":0.3041171274,"remaining_time":1.683576516},
{"learn":[4.968328804],"iteration":153,"passed_time":0.3055173293,"remaining_time":1.678361432},
{"learn":[4.9640736],"iteration":154,"passed_time":0.3066900238,"remaining_time":1.671955291},
{"learn":[4.960865882],"iteration":155,"passed_time":0.3081062123,"remaining_time":1.66693361},
{"learn":[4.957014156],"iteration":156,"passed_time":0.3093674791,"remaining_time":1.661126018},
{"learn":[4.952244852],"iteration":157,"passed_time":0.3103714451,"remaining_time":1.65400479},
{"learn":[4.949695675],"iteration":158,"passed_time":0.3115487967,"remaining_time":1.647877598},
{"learn":[4.946584698],"iteration":159,"passed_time":0.3126610397,"remaining_time":1.641470459},
{"learn":[4.940192834],"iteration":160,"passed_time":0.3138315934,"remaining_time":1.635432962},
{"learn":[4.936727994],"iteration":161,"passed_time":0.3148866721,"remaining_time":1.628858217},
{"learn":[4.932342063],"iteration":162,"passed_time":0.3159181204,"remaining_time":1.622229858},
{"learn":[4.925830838],"iteration":163,"passed_time":0.316926511,"remaining_time":1.615552215},
{"learn":[4.922571773],"iteration":164,"passed_time":0.3178773598,"remaining_time":1.608652093},
{"learn":[4.918395814],"iteration":165,"passed_time":0.3188044252,"remaining_time":1.60170416},
{"learn":[4.911142452],"iteration":166,"passed_time":0.319935165,"remaining_time":1.595844266},
{"learn":[4.908276131],"iteration":167,"passed_time":0.3211063585,"remaining_time":1.590241013},
{"learn":[4.904584645],"iteration":168,"passed_time":0.322923091,"remaining_time":1.58786443},
{"learn":[4.89795517],"iteration":169,"passed_time":0.3242951989,"remaining_time":1.583323618},
{"learn":[4.895556491],"iteration":170,"passed_time":0.3255754092,"remaining_time":1.578374352},
{"learn":[4.890591233],"iteration":171,"passed_time":0.3266181161,"remaining_time":1.57232442},
{"learn":[4.884629277],"iteration":172,"passed_time":0.3276376154,"remaining_time":1.566221433},
{"learn":[4.880550786],"iteration":173,"passed_time":0.3285403878,"remaining_time":1.55962276},
{"learn":[4.876384842],"iteration":174,"passed_time":0.3294971506,"remaining_time":1.55334371},
{"learn":[4.872638238],"iteration":175,"passed_time":0.3303909709,"remaining_time":1.546830455},
{"learn":[4.869137118],"iteration":176,"passed_time":0.3313905131,"remaining_time":1.540872273},
{"learn":[4.863587157],"iteration":177,"passed_time":0.3325156355,"remaining_time":1.535549733},
{"learn":[4.858028614],"iteration":178,"passed_time":0.3335768611,"remaining_time":1.529981022},
{"learn":[4.853838176],"iteration":179,"passed_time":0.3346251668,"remaining_time":1.524403537},
{"learn":[4.853462329],"iteration":180,"passed_time":0.3353747352,"remaining_time":1.517524354},
{"learn":[4.851573196],"iteration":181,"passed_time":0.3365727264,"remaining_time":1.512727968},
{"learn":[4.848442087],"iteration":182,"passed_time":0.3376592115,"remaining_time":1.507473092},
{"learn":[4.845547104],"iteration":183,"passed_time":0.3387203505,"remaining_time":1.50215112},
{"learn":[4.839868817],"iteration":184,"passed_time":0.3397203506,"remaining_time":1.496605869},
{"learn":[4.836336958],"iteration":185,"passed_time":0.3407604232,"remaining_time":1.491284863},
{"learn":[4.831124789],"iteration":186,"passed_time":0.3419237185,"remaining_time":1.486545364},
{"learn":[4.827407333],"iteration":187,"passed_time":0.343044495,"remaining_time":1.481660266},
{"learn":[4.824088918],"iteration":188,"passed_time":0.3442085296,"remaining_time":1.477000622},
{"learn":[4.820934539],"iteration":189,"passed_time":0.3452307693,"remaining_time":1.47177328},
{"learn":[4.816975227],"iteration":190,"passed_time":0.3462943418,"remaining_time":1.466765039},
{"learn":[4.812340486],"iteration":191,"passed_time":0.3473880027,"remaining_time":1.461924512},
{"learn":[4.806402747],"iteration":192,"passed_time":0.3485304487,"remaining_time":1.457326798},
{"learn":[4.801521788],"iteration":193,"passed_time":0.3496494354,"remaining_time":1.452667242},
{"learn":[4.797601172],"iteration":194,"passed_time":0.3514514378,"remaining_time":1.450863628},
{"learn":[4.792694629],"iteration":195,"passed_time":0.3527411799,"remaining_time":1.446958718},
{"learn":[4.789794613],"iteration":196,"passed_time":0.3539643436,"remaining_time":1.442808974},
{"learn":[4.785367055],"iteration":197,"passed_time":0.3550837144,"remaining_time":1.438268379},
{"learn":[4.780376856],"iteration":198,"passed_time":0.3562216761,"remaining_time":1.433836998},
{"learn":[4.776691261],"iteration":199,"passed_time":0.3574740729,"remaining_time":1.429896292},
{"learn":[4.773470753],"iteration":200,"passed_time":0.3586479746,"remaining_time":1.425670307},
{"learn":[4.77207327],"iteration":201,"passed_time":0.3596486539,"remaining_time":1.420790227},
{"learn":[4.767347177],"iteration":202,"passed_time":0.3606854999,"remaining_time":1.416090362},
{"learn":[4.763983068],"iteration":203,"passed_time":0.3617003673,"remaining_time":1.411340649},
{"learn":[4.761588849],"iteration":204,"passed_time":0.3626983173,"remaining_time":1.406561767},
{"learn":[4.758558086],"iteration":205,"passed_time":0.3638454875,"remaining_time":1.402394743},
{"learn":[4.753678804],"iteration":206,"passed_time":0.3656048664,"remaining_time":1.400602218},
{"learn":[4.746510889],"iteration":207,"passed_time":0.3674731613,"remaining_time":1.39922473},
{"learn":[4.744840601],"iteration":208,"passed_time":0.3692091273,"remaining_time":1.397341721},
{"learn":[4.741702222],"iteration":209,"passed_time":0.3706428842,"remaining_time":1.394323231},
{"learn":[4.739352853],"iteration":210,"passed_time":0.3720541616,"remaining_time":1.391235704},
{"learn":[4.735539287],"iteration":211,"passed_time":0.3732671183,"remaining_time":1.387426836},
{"learn":[4.730726751],"iteration":212,"passed_time":0.3744024108,"remaining_time":1.383355386},
{"learn":[4.726416092],"iteration":213,"passed_time":0.3755698356,"remaining_time":1.379429396},
{"learn":[4.721293082],"iteration":214,"passed_time":0.3769128354,"remaining_time":1.37617012},
{"learn":[4.718443695],"iteration":215,"passed_time":0.3783625003,"remaining_time":1.373315742},
{"learn":[4.711627962],"iteration":216,"passed_time":0.3797254199,"remaining_time":1.370161308},
{"learn":[4.709790764],"iteration":217,"passed_time":0.3814055783,"remaining_time":1.368161295},
{"learn":[4.706913073],"iteration":218,"passed_time":0.3828111426,"remaining_time":1.365184942},
{"learn":[4.703846389],"iteration":219,"passed_time":0.3842479326,"remaining_time":1.362333579},
{"learn":[4.701001135],"iteration":220,"passed_time":0.385463123,"remaining_time":1.358713904},
{"learn":[4.700380864],"iteration":221,"passed_time":0.386745516,"remaining_time":1.355351403},
{"learn":[4.695837486],"iteration":222,"passed_time":0.3881186814,"remaining_time":1.352323836},
{"learn":[4.691242996],"iteration":223,"passed_time":0.3893663872,"remaining_time":1.348876413},
{"learn":[4.690284609],"iteration":224,"passed_time":0.39117871,"remaining_time":1.347393334},
{"learn":[4.68827119],"iteration":225,"passed_time":0.3926995296,"remaining_time":1.344909008},
{"learn":[4.686922425],"iteration":226,"passed_time":0.3941410065,"remaining_time":1.342162987},
{"learn":[4.686085874],"iteration":227,"passed_time":0.3955939581,"remaining_time":1.339467261},
{"learn":[4.683230741],"iteration":228,"passed_time":0.3972029725,"remaining_time":1.337307824},
{"learn":[4.6773487],"iteration":229,"passed_time":0.3986735629,"remaining_time":1.334689754},
{"learn":[4.671462906],"iteration":230,"passed_time":0.3998107206,"remaining_time":1.33097162},
{"learn":[4.664799601],"iteration":231,"passed_time":0.4010735862,"remaining_time":1.327691872},
{"learn":[4.660979386],"iteration":232,"passed_time":0.4022929787,"remaining_time":1.324286329},
{"learn":[4.656281279],"iteration":233,"passed_time":0.4034964522,"remaining_time":1.32084736},
{"learn":[4.651997094],"iteration":234,"passed_time":0.4047595619,"remaining_time":1.317621552},
{"learn":[4.650151977],"iteration":235,"passed_time":0.4061490185,"remaining_time":1.314821399},
{"learn":[4.648478046],"iteration":236,"passed_time":0.4074497773,"remaining_time":1.311747595},
{"learn":[4.646364602],"iteration":237,"passed_time":0.4087093193,"remaining_time":1.308556728},
{"learn":[4.642635873],"iteration":238,"passed_time":0.4102561402,"remaining_time":1.306296748},
{"learn":[4.640860821],"iteration":239,"passed_time":0.4114742078,"remaining_time":1.303001658},
{"learn":[4.639446822],"iteration":240,"passed_time":0.4126526444,"remaining_time":1.299598992},
{"learn":[4.637120072],"iteration":241,"passed_time":0.414094481,"remaining_time":1.297039738},
{"learn":[4.633769267],"iteration":242,"passed_time":0.4153862765,"remaining_time":1.294022269},
{"learn":[4.630491517],"iteration":243,"passed_time":0.4166815584,"remaining_time":1.291029747},
{"learn":[4.627813333],"iteration":244,"passed_time":0.4179134694,"remaining_time":1.287855793},
{"learn":[4.622496304],"iteration":245,"passed_time":0.4191716261,"remaining_time":1.284778073},
{"learn":[4.618979301],"iteration":246,"passed_time":0.4205259571,"remaining_time":1.282008282},
{"learn":[4.616563458],"iteration":247,"passed_time":0.4216960416,"remaining_time":1.278691223},
{"learn":[4.614759385],"iteration":248,"passed_time":0.4231974975,"remaining_time":1.276390846},
{"learn":[4.61251363],"iteration":249,"passed_time":0.4244585568,"remaining_time":1.27337567},
{"learn":[4.608796693],"iteration":250,"passed_time":0.425924914,"remaining_time":1.270987094},
{"learn":[4.60847774],"iteration":251,"passed_time":0.4271526158,"remaining_time":1.267897447},
{"learn":[4.605195659],"iteration":252,"passed_time":0.4283376199,"remaining_time":1.264696451},
{"learn":[4.60103766],"iteration":253,"passed_time":0.4297415717,"remaining_time":1.26215438},
{"learn":[4.599325598],"iteration":254,"passed_time":0.431013546,"remaining_time":1.259235654},
{"learn":[4.597012808],"iteration":255,"passed_time":0.4324269974,"remaining_time":1.256740961},
{"learn":[4.594161533],"iteration":256,"passed_time":0.4341691119,"remaining_time":1.255204864},
{"learn":[4.592197259],"iteration":257,"passed_time":0.4354809474,"remaining_time":1.252429701},
{"learn":[4.58952828],"iteration":258,"passed_time":0.4369780773,"remaining_time":1.250195966},
{"learn":[4.585816572],"iteration":259,"passed_time":0.4384001053,"remaining_time":1.247754146},
{"learn":[4.582934052],"iteration":260,"passed_time":0.439742844,"remaining_time":1.245095639},
{"learn":[4.582234842],"iteration":261,"passed_time":0.4412066534,"remaining_time":1.242788207},
{"learn":[4.57571562],"iteration":262,"passed_time":0.4426117039,"remaining_time":1.240322531},
{"learn":[4.571197349],"iteration":263,"passed_time":0.444063069,"remaining_time":1.237994011},
{"learn":[4.56723703],"iteration":264,"passed_time":0.4453481647,"remaining_time":1.235210948},
{"learn":[4.560335567],"iteration":265,"passed_time":0.4475498053,"remaining_time":1.23496826},
{"learn":[4.554709345],"iteration":266,"passed_time":0.4505518859,"remaining_time":1.236908361},
{"learn":[4.552806306],"iteration":267,"passed_time":0.4531447804,"remaining_time":1.237693952},
{"learn":[4.550766241],"iteration":268,"passed_time":0.4568450879,"remaining_time":1.241463789},
{"learn":[4.549216045],"iteration":269,"passed_time":0.4603458537,"remaining_time":1.24463879},
{"learn":[4.547687452],"iteration":270,"passed_time":0.462497878,"remaining_time":1.244136358},
{"learn":[4.545642435],"iteration":271,"passed_time":0.4664223561,"remaining_time":1.248365718},
{"learn":[4.543930359],"iteration":272,"passed_time":0.4689125116,"remaining_time":1.248715736},
{"learn":[4.541029943],"iteration":273,"passed_time":0.4716112576,"remaining_time":1.249597712},
{"learn":[4.537781449],"iteration":274,"passed_time":0.4732785963,"remaining_time":1.247734481},
{"learn":[4.53066128],"iteration":275,"passed_time":0.475340379,"remaining_time":1.246907371},
{"learn":[4.526763956],"iteration":276,"passed_time":0.4770175831,"remaining_time":1.245067554},
{"learn":[4.522036004],"iteration":277,"passed_time":0.4788294733,"remaining_time":1.243578704},
{"learn":[4.515307629],"iteration":278,"passed_time":0.4806738958,"remaining_time":1.242171609},
{"learn":[4.51109143],"iteration":279,"passed_time":0.4825886244,"remaining_time":1.240942177},
{"learn":[4.508233494],"iteration":280,"passed_time":0.4845132002,"remaining_time":1.239733064},
{"learn":[4.502555629],"iteration":281,"passed_time":0.4864363238,"remaining_time":1.238515179},
{"learn":[4.500081355],"iteration":282,"passed_time":0.4882656789,"remaining_time":1.237054741},
{"learn":[4.495281743],"iteration":283,"passed_time":0.489846102,"remaining_time":1.234964116},
{"learn":[4.492138869],"iteration":284,"passed_time":0.4916830076,"remaining_time":1.233520528},
{"learn":[4.491708261],"iteration":285,"passed_time":0.4934815994,"remaining_time":1.231978538},
{"learn":[4.489398865],"iteration":286,"passed_time":0.4954458917,"remaining_time":1.230846414},
{"learn":[4.485796373],"iteration":287,"passed_time":0.4973532831,"remaining_time":1.229567839},
{"learn":[4.479542205],"iteration":288,"passed_time":0.5010366348,"remaining_time":1.232654143},
{"learn":[4.475986993],"iteration":289,"passed_time":0.5034356349,"remaining_time":1.232549313},
{"learn":[4.468661855],"iteration":290,"passed_time":0.5055521299,"remaining_time":1.231740413},
{"learn":[4.463785664],"iteration":291,"passed_time":0.507820511,"remaining_time":1.231290828},
{"learn":[4.460445831],"iteration":292,"passed_time":0.5110021237,"remaining_time":1.233032428},
{"learn":[4.45692492],"iteration":293,"passed_time":0.5132343945,"remaining_time":1.232460825},
{"learn":[4.454031688],"iteration":294,"passed_time":0.5148645354,"remaining_time":1.230438975},
{"learn":[4.451672391],"iteration":295,"passed_time":0.5169685928,"remaining_time":1.229546923},
{"learn":[4.45031553],"iteration":296,"passed_time":0.5190031484,"remaining_time":1.2284822},
{"learn":[4.446782666],"iteration":297,"passed_time":0.5211580445,"remaining_time":1.227694454},
{"learn":[4.444369689],"iteration":298,"passed_time":0.5230094043,"remaining_time":1.226185928},
{"learn":[4.44411683],"iteration":299,"passed_time":0.5252320545,"remaining_time":1.225541461},
{"learn":[4.440876943],"iteration":300,"passed_time":0.5268966105,"remaining_time":1.223590468},
{"learn":[4.439336453],"iteration":301,"passed_time":0.5286935753,"remaining_time":1.221947403},
{"learn":[4.436666901],"iteration":302,"passed_time":0.530950205,"remaining_time":1.221360703},
{"learn":[4.433043336],"iteration":303,"passed_time":0.5338279594,"remaining_time":1.222185065},
{"learn":[4.431419305],"iteration":304,"passed_time":0.5359510484,"remaining_time":1.221265504},
{"learn":[4.428859646],"iteration":305,"passed_time":0.5381910653,"remaining_time":1.220603266},
{"learn":[4.424552441],"iteration":306,"passed_time":0.5403428127,"remaining_time":1.219731496},
{"learn":[4.422706391],"iteration":307,"passed_time":0.5421946726,"remaining_time":1.218177641},
{"learn":[4.421427994],"iteration":308,"passed_time":0.5446026091,"remaining_time":1.217865382},
{"learn":[4.418733158],"iteration":309,"passed_time":0.5485962537,"remaining_time":1.221069081},
{"learn":[4.415656941],"iteration":310,"passed_time":0.5527966898,"remaining_time":1.224684628},
{"learn":[4.410747417],"iteration":311,"passed_time":0.5543761714,"remaining_time":1.222470532},
{"learn":[4.408126521],"iteration":312,"passed_time":0.5562646932,"remaining_time":1.220938799},
{"learn":[4.407843853],"iteration":313,"passed_time":0.558290821,"remaining_time":1.219705424},
{"learn":[4.405219398],"iteration":314,"passed_time":0.5602282915,"remaining_time":1.218274221},
{"learn":[4.402708465],"iteration":315,"passed_time":0.5629076684,"remaining_time":1.218445713},
{"learn":[4.40104971],"iteration":316,"passed_time":0.5652684535,"remaining_time":1.217912788},
{"learn":[4.400830038],"iteration":317,"passed_time":0.567211235,"remaining_time":1.216471894},
{"learn":[4.39784288],"iteration":318,"passed_time":0.5689386157,"remaining_time":1.214568017},
{"learn":[4.393741845],"iteration":319,"passed_time":0.5705797833,"remaining_time":1.21248204},
{"learn":[4.393425936],"iteration":320,"passed_time":0.5725512916,"remaining_time":1.211097592},
{"learn":[4.390505974],"iteration":321,"passed_time":0.5743241218,"remaining_time":1.209291163},
{"learn":[4.390305136],"iteration":322,"passed_time":0.5757099926,"remaining_time":1.206673885},
{"learn":[4.38568203],"iteration":323,"passed_time":0.5777260701,"remaining_time":1.205379085},
{"learn":[4.383057135],"iteration":324,"passed_time":0.580116255,"remaining_time":1.204856837},
{"learn":[4.380662684],"iteration":325,"passed_time":0.5833618143,"remaining_time":1.206091604},
{"learn":[4.37805727],"iteration":326,"passed_time":0.5848532651,"remaining_time":1.20368883},
{"learn":[4.373708319],"iteration":327,"passed_time":0.5865582752,"remaining_time":1.201729149},
{"learn":[4.36887921],"iteration":328,"passed_time":0.5883388979,"remaining_time":1.199925229},
{"learn":[4.367895929],"iteration":329,"passed_time":0.5898580284,"remaining_time":1.197590542},
{"learn":[4.362140573],"iteration":330,"passed_time":0.5937561501,"remaining_time":1.200069077},
{"learn":[4.361931924],"iteration":331,"passed_time":0.5963410146,"remaining_time":1.199866861},
{"learn":[4.359656377],"iteration":332,"passed_time":0.5980458759,"remaining_time":1.197887685},
{"learn":[4.354281355],"iteration":333,"passed_time":0.5996919828,"remaining_time":1.195792996},
{"learn":[4.348589447],"iteration":334,"passed_time":0.6012712067,"remaining_time":1.193568216},
{"learn":[4.346355698],"iteration":335,"passed_time":0.6030995762,"remaining_time":1.191839639},
{"learn":[4.343894047],"iteration":336,"passed_time":0.6047732865,"remaining_time":1.189806199},
{"learn":[4.341561356],"iteration":337,"passed_time":0.6066348643,"remaining_time":1.188142841},
{"learn":[4.338869061],"iteration":338,"passed_time":0.6104356108,"remaining_time":1.190259406},
{"learn":[4.333720063],"iteration":339,"passed_time":0.6125560501,"remaining_time":1.189079391},
{"learn":[4.330892223],"iteration":340,"passed_time":0.6143400058,"remaining_time":1.187243589},
{"learn":[4.328311474],"iteration":341,"passed_time":0.6161388128,"remaining_time":1.185436663},
{"learn":[4.324580133],"iteration":342,"passed_time":0.6178091099,"remaining_time":1.18338363},
{"learn":[4.323354432],"iteration":343,"passed_time":0.6192527899,"remaining_time":1.180900669},
{"learn":[4.323159553],"iteration":344,"passed_time":0.6207292831,"remaining_time":1.17848603},
{"learn":[4.318639682],"iteration":345,"passed_time":0.6230292574,"remaining_time":1.177633336},
{"learn":[4.312712208],"iteration":346,"passed_time":0.6250071025,"remaining_time":1.176166104},
{"learn":[4.311461062],"iteration":347,"passed_time":0.6267589988,"remaining_time":1.174272607},
{"learn":[4.311178356],"iteration":348,"passed_time":0.6283653146,"remaining_time":1.172108366},
{"learn":[4.311102505],"iteration":349,"passed_time":0.6297938185,"remaining_time":1.169617091},
{"learn":[4.310232308],"iteration":350,"passed_time":0.6310969762,"remaining_time":1.166900107},
{"learn":[4.305128197],"iteration":351,"passed_time":0.6326626473,"remaining_time":1.164674419},
{"learn":[4.304595496],"iteration":352,"passed_time":0.634144914,"remaining_time":1.162299602},
{"learn":[4.3004992],"iteration":353,"passed_time":0.6359636295,"remaining_time":1.160543799},
{"learn":[4.297581524],"iteration":354,"passed_time":0.6392759384,"remaining_time":1.161501353},
{"learn":[4.297355825],"iteration":355,"passed_time":0.6410650034,"remaining_time":1.159679388},
{"learn":[4.295758715],"iteration":356,"passed_time":0.6428047787,"remaining_time":1.157768831},
{"learn":[4.292500657],"iteration":357,"passed_time":0.6444338132,"remaining_time":1.155660637},
{"learn":[4.290797586],"iteration":358,"passed_time":0.6461183022,"remaining_time":1.153654127},
{"learn":[4.286410608],"iteration":359,"passed_time":0.6476502172,"remaining_time":1.151378164},
{"learn":[4.280278245],"iteration":360,"passed_time":0.6489900231,"remaining_time":1.148766274},
{"learn":[4.279941283],"iteration":361,"passed_time":0.650151197,"remaining_time":1.145846585},
{"learn":[4.274426275],"iteration":362,"passed_time":0.6520647785,"remaining_time":1.144256925},
{"learn":[4.273567658],"iteration":363,"passed_time":0.6539008573,"remaining_time":1.142530069},
{"learn":[4.269488271],"iteration":364,"passed_time":0.6556335437,"remaining_time":1.14062274},
{"learn":[4.266838205],"iteration":365,"passed_time":0.6569103049,"remaining_time":1.137926594},
{"learn":[4.263456509],"iteration":366,"passed_time":0.6583514155,"remaining_time":1.135521651},
{"learn":[4.260360204],"iteration":367,"passed_time":0.6596684228,"remaining_time":1.132908813},
{"learn":[4.255120549],"iteration":368,"passed_time":0.6609306427,"remaining_time":1.13020931},
{"learn":[4.252582211],"iteration":369,"passed_time":0.6621292709,"remaining_time":1.127409299},
{"learn":[4.247857931],"iteration":370,"passed_time":0.6635767816,"remaining_time":1.12503988},
{"learn":[4.245288911],"iteration":371,"passed_time":0.6648827337,"remaining_time":1.122436443},
{"learn":[4.24048515],"iteration":372,"passed_time":0.6669069689,"remaining_time":1.121047371},
{"learn":[4.2378365],"iteration":373,"passed_time":0.6686064827,"remaining_time":1.119111386},
{"learn":[4.236751063],"iteration":374,"passed_time":0.6704162309,"remaining_time":1.117360385},
{"learn":[4.233240093],"iteration":375,"passed_time":0.671962077,"remaining_time":1.115171107},
{"learn":[4.230358421],"iteration":376,"passed_time":0.6732497379,"remaining_time":1.112558586},
{"learn":[4.225853583],"iteration":377,"passed_time":0.6749399711,"remaining_time":1.110615508},
{"learn":[4.224702126],"iteration":378,"passed_time":0.6762408044,"remaining_time":1.108035724},
{"learn":[4.224361982],"iteration":379,"passed_time":0.6776964367,"remaining_time":1.105715239},
{"learn":[4.223787954],"iteration":380,"passed_time":0.6791421539,"remaining_time":1.103383184},
{"learn":[4.22144054],"iteration":381,"passed_time":0.680500861,"remaining_time":1.100915006},
{"learn":[4.217739335],"iteration":382,"passed_time":0.6828284018,"remaining_time":1.100013378},
{"learn":[4.215611665],"iteration":383,"passed_time":0.6842336744,"remaining_time":1.097624853},
{"learn":[4.210236863],"iteration":384,"passed_time":0.6859659969,"remaining_time":1.095763865},
{"learn":[4.208454294],"iteration":385,"passed_time":0.6875112819,"remaining_time":1.093606029},
{"learn":[4.207446501],"iteration":386,"passed_time":0.6888427836,"remaining_time":1.09111273},
{"learn":[4.204985442],"iteration":387,"passed_time":0.690139566,"remaining_time":1.088570656},
{"learn":[4.202796622],"iteration":388,"passed_time":0.6914034714,"remaining_time":1.085983345},
{"learn":[4.199774004],"iteration":389,"passed_time":0.6926726427,"remaining_time":1.083411057},
{"learn":[4.199458358],"iteration":390,"passed_time":0.6941051784,"remaining_time":1.081099881},
{"learn":[4.19751254],"iteration":391,"passed_time":0.6958373923,"remaining_time":1.079257996},
{"learn":[4.195201346],"iteration":392,"passed_time":0.6979554069,"remaining_time":1.07801255},
{"learn":[4.190593508],"iteration":393,"passed_time":0.7000840565,"remaining_time":1.076779031},
{"learn":[4.187212054],"iteration":394,"passed_time":0.7014626755,"remaining_time":1.074392199},
{"learn":[4.184984466],"iteration":395,"passed_time":0.7032851153,"remaining_time":1.072687398},
{"learn":[4.182832144],"iteration":396,"passed_time":0.7045926103,"remaining_time":1.070199859},
{"learn":[4.179752812],"iteration":397,"passed_time":0.7060892131,"remaining_time":1.068004287},
{"learn":[4.17878934],"iteration":398,"passed_time":0.7075789442,"remaining_time":1.065801868},
{"learn":[4.174548229],"iteration":399,"passed_time":0.708971736,"remaining_time":1.063457604},
{"learn":[4.168872556],"iteration":400,"passed_time":0.7103779928,"remaining_time":1.061138199},
{"learn":[4.163926494],"iteration":401,"passed_time":0.711697356,"remaining_time":1.058694077},
{"learn":[4.159485076],"iteration":402,"passed_time":0.7132026775,"remaining_time":1.056531014},
{"learn":[4.155926102],"iteration":403,"passed_time":0.7145638346,"remaining_time":1.054158528},
{"learn":[4.153540115],"iteration":404,"passed_time":0.7159258156,"remaining_time":1.051792248},
{"learn":[4.150983044],"iteration":405,"passed_time":0.7173136722,"remaining_time":1.049468772},
{"learn":[4.146539132],"iteration":406,"passed_time":0.7187977417,"remaining_time":1.047290076},
{"learn":[4.144869174],"iteration":407,"passed_time":0.7200793912,"remaining_time":1.044821077},
{"learn":[4.142825962],"iteration":408,"passed_time":0.7212290997,"remaining_time":1.042167232},
{"learn":[4.142467378],"iteration":409,"passed_time":0.7223622538,"remaining_time":1.039496902},
{"learn":[4.141800768],"iteration":410,"passed_time":0.7236024873,"remaining_time":1.036987506},
{"learn":[4.140107084],"iteration":411,"passed_time":0.7251525235,"remaining_time":1.034926417},
{"learn":[4.136243196],"iteration":412,"passed_time":0.7268322373,"remaining_time":1.033052115},
{"learn":[4.133618439],"iteration":413,"passed_time":0.72907953,"remaining_time":1.031982137},
{"learn":[4.131053025],"iteration":414,"passed_time":0.7306121047,"remaining_time":1.029898991},
{"learn":[4.128379975],"iteration":415,"passed_time":0.732245633,"remaining_time":1.027960216},
{"learn":[4.127068571],"iteration":416,"passed_time":0.7337579237,"remaining_time":1.025853404},
{"learn":[4.125969877],"iteration":417,"passed_time":0.7351931808,"remaining_time":1.02364218},
{"learn":[4.123893633],"iteration":418,"passed_time":0.7365111151,"remaining_time":1.021271976},
{"learn":[4.119643722],"iteration":419,"passed_time":0.7381036522,"remaining_time":1.019285996},
{"learn":[4.11465686],"iteration":420,"passed_time":0.7398067424,"remaining_time":1.017453928},
{"learn":[4.111565986],"iteration":421,"passed_time":0.7413571508,"remaining_time":1.015413349},
{"learn":[4.106322452],"iteration":422,"passed_time":0.7428320572,"remaining_time":1.013272097},
{"learn":[4.104222175],"iteration":423,"passed_time":0.7441313406,"remaining_time":1.010895406},
{"learn":[4.103008002],"iteration":424,"passed_time":0.7458016482,"remaining_time":1.009025759},
{"learn":[4.099176337],"iteration":425,"passed_time":0.7471420496,"remaining_time":1.006712527},
{"learn":[4.096525716],"iteration":426,"passed_time":0.748719262,"remaining_time":1.004721633},
{"learn":[4.094967724],"iteration":427,"passed_time":0.7500671485,"remaining_time":1.002426189},
{"learn":[4.094683584],"iteration":428,"passed_time":0.7511117406,"remaining_time":0.9997314775},
{"learn":[4.091096563],"iteration":429,"passed_time":0.752318908,"remaining_time":0.9972599479},
{"learn":[4.089178677],"iteration":430,"passed_time":0.7535158446,"remaining_time":0.9947807786},
{"learn":[4.085335077],"iteration":431,"passed_time":0.7548405681,"remaining_time":0.9924755618},
{"learn":[4.084852122],"iteration":432,"passed_time":0.7560233531,"remaining_time":0.9899890097},
{"learn":[4.080322952],"iteration":433,"passed_time":0.7575956874,"remaining_time":0.9880164955},
{"learn":[4.077449519],"iteration":434,"passed_time":0.7591536628,"remaining_time":0.9860271713},
{"learn":[4.076568374],"iteration":435,"passed_time":0.7603486222,"remaining_time":0.9835702361},
{"learn":[4.076071793],"iteration":436,"passed_time":0.7616305096,"remaining_time":0.9812310685},
{"learn":[4.075027644],"iteration":437,"passed_time":0.7628314046,"remaining_time":0.9787928068},
{"learn":[4.07020837],"iteration":438,"passed_time":0.7641075433,"remaining_time":0.9764563367},
{"learn":[4.06833694],"iteration":439,"passed_time":0.7653578188,"remaining_time":0.9740917694},
{"learn":[4.063936568],"iteration":440,"passed_time":0.7665028694,"remaining_time":0.9715988752},
{"learn":[4.061734926],"iteration":441,"passed_time":0.7677076975,"remaining_time":0.9691875457},
{"learn":[4.060815619],"iteration":442,"passed_time":0.7689258588,"remaining_time":0.9667984274},
{"learn":[4.056407489],"iteration":443,"passed_time":0.7701950284,"remaining_time":0.964478459},
{"learn":[4.05238936],"iteration":444,"passed_time":0.7713827299,"remaining_time":0.9620616069},
{"learn":[4.049685254],"iteration":445,"passed_time":0.7726702126,"remaining_time":0.9597742103},
{"learn":[4.045162016],"iteration":446,"passed_time":0.7740158393,"remaining_time":0.9575632196},
{"learn":[4.042955482],"iteration":447,"passed_time":0.7752417132,"remaining_time":0.9552085395},
{"learn":[4.041467663],"iteration":448,"passed_time":0.7764027545,"remaining_time":0.9527793268},
{"learn":[4.038920476],"iteration":449,"passed_time":0.7776534457,"remaining_time":0.9504653225},
{"learn":[4.036694383],"iteration":450,"passed_time":0.7787973321,"remaining_time":0.9480260207},
{"learn":[4.034999007],"iteration":451,"passed_time":0.7800617079,"remaining_time":0.9457385308},
{"learn":[4.031928018],"iteration":452,"passed_time":0.7812457609,"remaining_time":0.9433585677},
{"learn":[4.028718143],"iteration":453,"passed_time":0.7824509744,"remaining_time":0.9410093216},
{"learn":[4.027401978],"iteration":454,"passed_time":0.7835323494,"remaining_time":0.9385167701},
{"learn":[4.025930598],"iteration":455,"passed_time":0.7847672072,"remaining_time":0.9362135104},
{"learn":[4.021074523],"iteration":456,"passed_time":0.7859303023,"remaining_time":0.933829659},
{"learn":[4.020268486],"iteration":457,"passed_time":0.7873165697,"remaining_time":0.9317152419},
{"learn":[4.017986361],"iteration":458,"passed_time":0.7888556589,"remaining_time":0.9297841209},
{"learn":[4.014814804],"iteration":459,"passed_time":0.7903744218,"remaining_time":0.927830843},
{"learn":[4.009704796],"iteration":460,"passed_time":0.791614376,"remaining_time":0.9255534679},
{"learn":[4.008440457],"iteration":461,"passed_time":0.7926457655,"remaining_time":0.9230377096},
{"learn":[4.004854849],"iteration":462,"passed_time":0.7938395824,"remaining_time":0.9207167511},
{"learn":[4.000898028],"iteration":463,"passed_time":0.7950408872,"remaining_time":0.9184093007},
{"learn":[3.996617985],"iteration":464,"passed_time":0.7963672953,"remaining_time":0.9162505441},
{"learn":[3.995443319],"iteration":465,"passed_time":0.7973612592,"remaining_time":0.9137144043},
{"learn":[3.990771995],"iteration":466,"passed_time":0.7983621631,"remaining_time":0.91119279},
{"learn":[3.989249359],"iteration":467,"passed_time":0.7993652319,"remaining_time":0.9086801354},
{"learn":[3.986599538],"iteration":468,"passed_time":0.8005037211,"remaining_time":0.9063272407},
{"learn":[3.985628919],"iteration":469,"passed_time":0.8014971155,"remaining_time":0.9038158962},
{"learn":[3.985086112],"iteration":470,"passed_time":0.8027411338,"remaining_time":0.9015924836},
{"learn":[3.98466839],"iteration":471,"passed_time":0.8037701939,"remaining_time":0.8991327593},
{"learn":[3.984233894],"iteration":472,"passed_time":0.8048823395,"remaining_time":0.8967716553},
{"learn":[3.981855845],"iteration":473,"passed_time":0.8060215718,"remaining_time":0.8944458792},
{"learn":[3.978684264],"iteration":474,"passed_time":0.8073545454,"remaining_time":0.8923392344},
{"learn":[3.974361269],"iteration":475,"passed_time":0.808398346,"remaining_time":0.8899175069},
{"learn":[3.972074049],"iteration":476,"passed_time":0.8096052184,"remaining_time":0.8876803547},
{"learn":[3.97191982],"iteration":477,"passed_time":0.8107228496,"remaining_time":0.8853500575},
{"learn":[3.969616848],"iteration":478,"passed_time":0.8118087926,"remaining_time":0.8829903569},
{"learn":[3.968533527],"iteration":479,"passed_time":0.812881172,"remaining_time":0.8806212697},
{"learn":[3.967568753],"iteration":480,"passed_time":0.8140180881,"remaining_time":0.8783272094},
{"learn":[3.966232553],"iteration":481,"passed_time":0.8151492987,"remaining_time":0.8760318189},
{"learn":[3.961522393],"iteration":482,"passed_time":0.8161997004,"remaining_time":0.8736547517},
{"learn":[3.955829553],"iteration":483,"passed_time":0.8177406942,"remaining_time":0.8718061946},
{"learn":[3.954248095],"iteration":484,"passed_time":0.8195079725,"remaining_time":0.8701991873},
{"learn":[3.951922606],"iteration":485,"passed_time":0.8210235987,"remaining_time":0.8683253698},
{"learn":[3.94978202],"iteration":486,"passed_time":0.8222152855,"remaining_time":0.8661117895},
{"learn":[3.949518999],"iteration":487,"passed_time":0.8232593969,"remaining_time":0.863747564},
{"learn":[3.945431216],"iteration":488,"passed_time":0.8244436621,"remaining_time":0.861535197},
{"learn":[3.943249086],"iteration":489,"passed_time":0.8257175208,"remaining_time":0.8594202767},
{"learn":[3.941981548],"iteration":490,"passed_time":0.8271406734,"remaining_time":0.8574635494},
{"learn":[3.936600517],"iteration":491,"passed_time":0.8281328238,"remaining_time":0.8550639725},
{"learn":[3.934476885],"iteration":492,"passed_time":0.8292067904,"remaining_time":0.8527542449},
{"learn":[3.93045798],"iteration":493,"passed_time":0.8302494779,"remaining_time":0.8504174814},
{"learn":[3.925977375],"iteration":494,"passed_time":0.831321123,"remaining_time":0.8481154891},
{"learn":[3.92457993],"iteration":495,"passed_time":0.8324639966,"remaining_time":0.8458908353},
{"learn":[3.919849146],"iteration":496,"passed_time":0.8337073262,"remaining_time":0.8437722034},
{"learn":[3.919681964],"iteration":497,"passed_time":0.8348157629,"remaining_time":0.8415211104},
{"learn":[3.917633027],"iteration":498,"passed_time":0.8361192169,"remaining_time":0.8394703962},
{"learn":[3.916616419],"iteration":499,"passed_time":0.8373104218,"remaining_time":0.8373104218},
{"learn":[3.912896166],"iteration":500,"passed_time":0.8387034884,"remaining_time":0.8353553707},
{"learn":[3.912769674],"iteration":501,"passed_time":0.8397708899,"remaining_time":0.8330794884},
{"learn":[3.909373788],"iteration":502,"passed_time":0.8407998841,"remaining_time":0.830770462},
{"learn":[3.906706036],"iteration":503,"passed_time":0.8418554266,"remaining_time":0.828492642},
{"learn":[3.903895664],"iteration":504,"passed_time":0.8428777612,"remaining_time":0.8261871125},
{"learn":[3.902982967],"iteration":505,"passed_time":0.8438828854,"remaining_time":0.8238698526},
{"learn":[3.900905528],"iteration":506,"passed_time":0.8450315629,"remaining_time":0.821697358},
{"learn":[3.897463465],"iteration":507,"passed_time":0.8463406529,"remaining_time":0.8196842544},
{"learn":[3.895918033],"iteration":508,"passed_time":0.8473183002,"remaining_time":0.8173541953},
{"learn":[3.893921936],"iteration":509,"passed_time":0.8485851963,"remaining_time":0.8153073455},
{"learn":[3.890237934],"iteration":510,"passed_time":0.8501021329,"remaining_time":0.8135028239},
{"learn":[3.887311613],"iteration":511,"passed_time":0.851351958,"remaining_time":0.8114448349},
{"learn":[3.884869735],"iteration":512,"passed_time":0.8525643391,"remaining_time":0.8093544506},
{"learn":[3.882101231],"iteration":513,"passed_time":0.8538830575,"remaining_time":0.8073680271},
{"learn":[3.88060368],"iteration":514,"passed_time":0.8551516527,"remaining_time":0.8053369933},
{"learn":[3.877726076],"iteration":515,"passed_time":0.8561710579,"remaining_time":0.8030751783},
{"learn":[3.874938145],"iteration":516,"passed_time":0.8572709192,"remaining_time":0.8008933346},
{"learn":[3.874340833],"iteration":517,"passed_time":0.8583856583,"remaining_time":0.7987295121},
{"learn":[3.873105224],"iteration":518,"passed_time":0.8594745805,"remaining_time":0.7965458058},
{"learn":[3.869800236],"iteration":519,"passed_time":0.8604800777,"remaining_time":0.7942893025},
{"learn":[3.867932518],"iteration":520,"passed_time":0.8614804151,"remaining_time":0.7920328577},
{"learn":[3.866666962],"iteration":521,"passed_time":0.8625075697,"remaining_time":0.7898057823},
{"learn":[3.865527652],"iteration":522,"passed_time":0.8638262003,"remaining_time":0.7878491348},
{"learn":[3.861900081],"iteration":523,"passed_time":0.8650014587,"remaining_time":0.7857646838},
{"learn":[3.858502887],"iteration":524,"passed_time":0.8661641228,"remaining_time":0.7836723016},
{"learn":[3.858335097],"iteration":525,"passed_time":0.8674830467,"remaining_time":0.7817242664},
{"learn":[3.855719306],"iteration":526,"passed_time":0.8686417189,"remaining_time":0.7796347875},
{"learn":[3.855137428],"iteration":527,"passed_time":0.8696618621,"remaining_time":0.777424998},
{"learn":[3.851985706],"iteration":528,"passed_time":0.870786958,"remaining_time":0.7753131517},
{"learn":[3.851051809],"iteration":529,"passed_time":0.8717750808,"remaining_time":0.7730835622},
{"learn":[3.850679146],"iteration":530,"passed_time":0.8727790944,"remaining_time":0.7708726841},
{"learn":[3.848179484],"iteration":531,"passed_time":0.8736983748,"remaining_time":0.7685918034},
{"learn":[3.844551071],"iteration":532,"passed_time":0.8746587313,"remaining_time":0.7663520216},
{"learn":[3.841604794],"iteration":533,"passed_time":0.8756552777,"remaining_time":0.7641486131},
{"learn":[3.83969656],"iteration":534,"passed_time":0.8767956338,"remaining_time":0.7620747098},
{"learn":[3.836811463],"iteration":535,"passed_time":0.8779468611,"remaining_time":0.7600137006},
{"learn":[3.834182551],"iteration":536,"passed_time":0.8789922286,"remaining_time":0.7578648079},
{"learn":[3.828012842],"iteration":537,"passed_time":0.8800268537,"remaining_time":0.7557107926},
{"learn":[3.826636176],"iteration":538,"passed_time":0.8811161854,"remaining_time":0.7536077207},
{"learn":[3.826189798],"iteration":539,"passed_time":0.8822611161,"remaining_time":0.7515557656},
{"learn":[3.824104738],"iteration":540,"passed_time":0.88329016,"remaining_time":0.7494088419},
{"learn":[3.82300218],"iteration":541,"passed_time":0.8843177767,"remaining_time":0.7472648372},
{"learn":[3.817146402],"iteration":542,"passed_time":0.8853883489,"remaining_time":0.7451610966},
{"learn":[3.814638044],"iteration":543,"passed_time":0.8866672095,"remaining_time":0.7432357491},
{"learn":[3.812979573],"iteration":544,"passed_time":0.8877703811,"remaining_time":0.741166098},
{"learn":[3.811938825],"iteration":545,"passed_time":0.8889194079,"remaining_time":0.7391381157},
{"learn":[3.811479418],"iteration":546,"passed_time":0.8900419515,"remaining_time":0.737091415},
{"learn":[3.80742981],"iteration":547,"passed_time":0.8911990717,"remaining_time":0.7350766066},
{"learn":[3.805097043],"iteration":548,"passed_time":0.8922428354,"remaining_time":0.732971801},
{"learn":[3.801577232],"iteration":549,"passed_time":0.8937310874,"remaining_time":0.7312345261},
{"learn":[3.799762083],"iteration":550,"passed_time":0.8947964916,"remaining_time":0.7291535839},
{"learn":[3.796393455],"iteration":551,"passed_time":0.8959342837,"remaining_time":0.7271350708},
{"learn":[3.793486459],"iteration":552,"passed_time":0.8985952029,"remaining_time":0.7263509145},
{"learn":[3.792006091],"iteration":553,"passed_time":0.8997595773,"remaining_time":0.7243551832},
{"learn":[3.78932128],"iteration":554,"passed_time":0.901258413,"remaining_time":0.7226306194},
{"learn":[3.787581812],"iteration":555,"passed_time":0.9023807891,"remaining_time":0.7206062417},
{"learn":[3.785308865],"iteration":556,"passed_time":0.9035881269,"remaining_time":0.7186526754},
{"learn":[3.78465475],"iteration":557,"passed_time":0.9049815623,"remaining_time":0.7168491945},
{"learn":[3.780498869],"iteration":558,"passed_time":0.9062184955,"remaining_time":0.7149237147},
{"learn":[3.778734909],"iteration":559,"passed_time":0.9074133969,"remaining_time":0.712967669},
{"learn":[3.778652349],"iteration":560,"passed_time":0.9086722229,"remaining_time":0.7110643598},
{"learn":[3.777928006],"iteration":561,"passed_time":0.9099168458,"remaining_time":0.7091522749},
{"learn":[3.776131406],"iteration":562,"passed_time":0.9119998537,"remaining_time":0.7078933145},
{"learn":[3.772925617],"iteration":563,"passed_time":0.9130786506,"remaining_time":0.7058551271},
{"learn":[3.7727745],"iteration":564,"passed_time":0.9141210928,"remaining_time":0.7037923458},
{"learn":[3.771763073],"iteration":565,"passed_time":0.9152443869,"remaining_time":0.7017951659},
{"learn":[3.768738162],"iteration":566,"passed_time":0.916522136,"remaining_time":0.699919021},
{"learn":[3.767220794],"iteration":567,"passed_time":0.9176819465,"remaining_time":0.6979552833},
{"learn":[3.766691102],"iteration":568,"passed_time":0.9188745264,"remaining_time":0.6960191931},
{"learn":[3.766259335],"iteration":569,"passed_time":0.9199981748,"remaining_time":0.6940337108},
{"learn":[3.76116362],"iteration":570,"passed_time":0.9212295686,"remaining_time":0.6921321978},
{"learn":[3.758633056],"iteration":571,"passed_time":0.9224410314,"remaining_time":0.6902181144},
{"learn":[3.754603809],"iteration":572,"passed_time":0.924184729,"remaining_time":0.6887031052},
{"learn":[3.754070549],"iteration":573,"passed_time":0.9254066813,"remaining_time":0.6868000806},
{"learn":[3.750534319],"iteration":574,"passed_time":0.9266682374,"remaining_time":0.6849286972},
{"learn":[3.746491516],"iteration":575,"passed_time":0.9281365871,"remaining_time":0.6832116544},
{"learn":[3.744210544],"iteration":576,"passed_time":0.929322195,"remaining_time":0.6812881949},
{"learn":[3.742929991],"iteration":577,"passed_time":0.9304661075,"remaining_time":0.6793368467},
{"learn":[3.740402992],"iteration":578,"passed_time":0.931898918,"remaining_time":0.6775983497},
{"learn":[3.739644243],"iteration":579,"passed_time":0.9332090572,"remaining_time":0.6757720759},
{"learn":[3.737529404],"iteration":580,"passed_time":0.9346004765,"remaining_time":0.6740061956},
{"learn":[3.737196923],"iteration":581,"passed_time":0.9358926139,"remaining_time":0.6721702966},
{"learn":[3.733954464],"iteration":582,"passed_time":0.9375561898,"remaining_time":0.6706019402},
{"learn":[3.731608623],"iteration":583,"passed_time":0.9389175164,"remaining_time":0.6688179569},
{"learn":[3.729843952],"iteration":584,"passed_time":0.9426054261,"remaining_time":0.6686859006},
{"learn":[3.727223798],"iteration":585,"passed_time":0.9440938224,"remaining_time":0.6669877858},
{"learn":[3.725351667],"iteration":586,"passed_time":0.9480167701,"remaining_time":0.6670032812},
{"learn":[3.725026912],"iteration":587,"passed_time":0.9493976037,"remaining_time":0.6652241713},
{"learn":[3.721974565],"iteration":588,"passed_time":0.9506552951,"remaining_time":0.663360486},
{"learn":[3.720269493],"iteration":589,"passed_time":0.9519300542,"remaining_time":0.6615107157},
{"learn":[3.718907466],"iteration":590,"passed_time":0.9531755213,"remaining_time":0.6596426197},
{"learn":[3.715602912],"iteration":591,"passed_time":0.9544960142,"remaining_time":0.6578283341},
{"learn":[3.714463059],"iteration":592,"passed_time":0.955852658,"remaining_time":0.6560405258},
{"learn":[3.710802077],"iteration":593,"passed_time":0.9570949996,"remaining_time":0.6541760435},
{"learn":[3.708032435],"iteration":594,"passed_time":0.9584449188,"remaining_time":0.6523868775},
{"learn":[3.703788939],"iteration":595,"passed_time":0.9604505665,"remaining_time":0.6510436726},
{"learn":[3.702500944],"iteration":596,"passed_time":0.9625465272,"remaining_time":0.6497592135},
{"learn":[3.698196925],"iteration":597,"passed_time":0.9640677856,"remaining_time":0.648085702},
{"learn":[3.69658891],"iteration":598,"passed_time":0.9654189704,"remaining_time":0.6462988433},
{"learn":[3.696124066],"iteration":599,"passed_time":0.966790874,"remaining_time":0.6445272493},
{"learn":[3.693537052],"iteration":600,"passed_time":0.968198962,"remaining_time":0.6427810081},
{"learn":[3.691343275],"iteration":601,"passed_time":0.969555024,"remaining_time":0.6410014943},
{"learn":[3.690973831],"iteration":602,"passed_time":0.9708554006,"remaining_time":0.6391867231},
{"learn":[3.686151073],"iteration":603,"passed_time":0.9720593075,"remaining_time":0.6373104069},
{"learn":[3.683921982],"iteration":604,"passed_time":0.973413244,"remaining_time":0.6355342667},
{"learn":[3.679975271],"iteration":605,"passed_time":0.974743001,"remaining_time":0.6337437993},
{"learn":[3.674047638],"iteration":606,"passed_time":0.9762185651,"remaining_time":0.6320492522},
{"learn":[3.673151794],"iteration":607,"passed_time":0.9776449352,"remaining_time":0.6303237082},
{"learn":[3.670953108],"iteration":608,"passed_time":0.9789681859,"remaining_time":0.6285329404},
{"learn":[3.6703947],"iteration":609,"passed_time":0.980456346,"remaining_time":0.6268491392},
{"learn":[3.668433805],"iteration":610,"passed_time":0.9819294162,"remaining_time":0.6251563714},
{"learn":[3.668304956],"iteration":611,"passed_time":0.9831398894,"remaining_time":0.6232978384},
{"learn":[3.667880012],"iteration":612,"passed_time":0.9843549339,"remaining_time":0.6214443058},
{"learn":[3.667282264],"iteration":613,"passed_time":0.9858444209,"remaining_time":0.6197653852},
{"learn":[3.664611483],"iteration":614,"passed_time":0.9875183011,"remaining_time":0.6182025137},
{"learn":[3.662543394],"iteration":615,"passed_time":0.9891035136,"remaining_time":0.6165840085},
{"learn":[3.659041959],"iteration":616,"passed_time":0.9908569071,"remaining_time":0.6150700088},
{"learn":[3.656868545],"iteration":617,"passed_time":0.9925695307,"remaining_time":0.6135300335},
{"learn":[3.654785614],"iteration":618,"passed_time":0.9953666138,"remaining_time":0.6126569949},
{"learn":[3.654566096],"iteration":619,"passed_time":0.9981029901,"remaining_time":0.6117405423},
{"learn":[3.651007045],"iteration":620,"passed_time":1.000154259,"remaining_time":0.6104001032},
{"learn":[3.648921786],"iteration":621,"passed_time":1.002278718,"remaining_time":0.6091018575},
{"learn":[3.647655706],"iteration":622,"passed_time":1.004598048,"remaining_time":0.6079188828},
{"learn":[3.647241144],"iteration":623,"passed_time":1.006310362,"remaining_time":0.6063665002},
{"learn":[3.644195689],"iteration":624,"passed_time":1.008270423,"remaining_time":0.6049622539},
{"learn":[3.642632246],"iteration":625,"passed_time":1.010166167,"remaining_time":0.6035178056},
{"learn":[3.642523322],"iteration":626,"passed_time":1.01117536,"remaining_time":0.6015445126},
{"learn":[3.641494659],"iteration":627,"passed_time":1.012972177,"remaining_time":0.6000408436},
{"learn":[3.63976496],"iteration":628,"passed_time":1.015085473,"remaining_time":0.5987229103},
{"learn":[3.637945652],"iteration":629,"passed_time":1.017085992,"remaining_time":0.5973362177},
{"learn":[3.636233667],"iteration":630,"passed_time":1.019045044,"remaining_time":0.5959233302},
{"learn":[3.635304404],"iteration":631,"passed_time":1.020586449,"remaining_time":0.5942655275},
{"learn":[3.632234951],"iteration":632,"passed_time":1.022443218,"remaining_time":0.5927909338},
{"learn":[3.631630987],"iteration":633,"passed_time":1.024061565,"remaining_time":0.5911774967},
{"learn":[3.630301009],"iteration":634,"passed_time":1.025985668,"remaining_time":0.5897397935},
{"learn":[3.629077964],"iteration":635,"passed_time":1.027824409,"remaining_time":0.5882517056},
{"learn":[3.628004522],"iteration":636,"passed_time":1.030947032,"remaining_time":0.5874941486},
{"learn":[3.625062876],"iteration":637,"passed_time":1.033071618,"remaining_time":0.5861628927},
{"learn":[3.624917986],"iteration":638,"passed_time":1.035383441,"remaining_time":0.5849349328},
{"learn":[3.622887087],"iteration":639,"passed_time":1.038020543,"remaining_time":0.5838865552},
{"learn":[3.621220865],"iteration":640,"passed_time":1.039633747,"remaining_time":0.5822597741},
{"learn":[3.621143844],"iteration":641,"passed_time":1.041415397,"remaining_time":0.5807269659},
{"learn":[3.620822821],"iteration":642,"passed_time":1.044599765,"remaining_time":0.5799721866},
{"learn":[3.619202826],"iteration":643,"passed_time":1.046904997,"remaining_time":0.5787238802},
{"learn":[3.618204882],"iteration":644,"passed_time":1.049627364,"remaining_time":0.5777018825},
{"learn":[3.614259666],"iteration":645,"passed_time":1.0512116,"remaining_time":0.576050939},
{"learn":[3.613415661],"iteration":646,"passed_time":1.052909018,"remaining_time":0.5744619525},
{"learn":[3.611096773],"iteration":647,"passed_time":1.05460356,"remaining_time":0.5728710698},
{"learn":[3.610820695],"iteration":648,"passed_time":1.056607766,"remaining_time":0.5714473432},
{"learn":[3.609290065],"iteration":649,"passed_time":1.059032772,"remaining_time":0.5702484159},
{"learn":[3.60897947],"iteration":650,"passed_time":1.062450053,"remaining_time":0.5695776784},
{"learn":[3.606570702],"iteration":651,"passed_time":1.069587194,"remaining_time":0.5708839623},
{"learn":[3.606292637],"iteration":652,"passed_time":1.073491906,"remaining_time":0.5704466942},
{"learn":[3.602753838],"iteration":653,"passed_time":1.078364154,"remaining_time":0.5705106991},
{"learn":[3.599755869],"iteration":654,"passed_time":1.087096863,"remaining_time":0.5725930044},
{"learn":[3.599509575],"iteration":655,"passed_time":1.098232086,"remaining_time":0.5759021914},
{"learn":[3.595337722],"iteration":656,"passed_time":1.10049881,"remaining_time":0.5745374304},
{"learn":[3.595168561],"iteration":657,"passed_time":1.103650086,"remaining_time":0.5736296801},
{"learn":[3.59290559],"iteration":658,"passed_time":1.107364252,"remaining_time":0.5730063881},
{"learn":[3.592015928],"iteration":659,"passed_time":1.109506063,"remaining_time":0.5715637295},
{"learn":[3.590680403],"iteration":660,"passed_time":1.111799448,"remaining_time":0.5701966914},
{"learn":[3.590361532],"iteration":661,"passed_time":1.113622054,"remaining_time":0.568586487},
{"learn":[3.589069739],"iteration":662,"passed_time":1.115787816,"remaining_time":0.5671500665},
{"learn":[3.585010186],"iteration":663,"passed_time":1.117860202,"remaining_time":0.5656641986},
{"learn":[3.582997552],"iteration":664,"passed_time":1.12402437,"remaining_time":0.5662378406},
{"learn":[3.582119256],"iteration":665,"passed_time":1.125918377,"remaining_time":0.5646497569},
{"learn":[3.579019356],"iteration":666,"passed_time":1.127867805,"remaining_time":0.5630884243},
{"learn":[3.57719559],"iteration":667,"passed_time":1.13084183,"remaining_time":0.5620351612},
{"learn":[3.574050046],"iteration":668,"passed_time":1.13304482,"remaining_time":0.5605946717},
{"learn":[3.572204518],"iteration":669,"passed_time":1.135753987,"remaining_time":0.5594012173},
{"learn":[3.569508025],"iteration":670,"passed_time":1.139932204,"remaining_time":0.5589235397},
{"learn":[3.566268704],"iteration":671,"passed_time":1.142144943,"remaining_time":0.5574755077},
{"learn":[3.562564052],"iteration":672,"passed_time":1.144515213,"remaining_time":0.5561017456},
{"learn":[3.561173586],"iteration":673,"passed_time":1.146641359,"remaining_time":0.554606948},
{"learn":[3.559551904],"iteration":674,"passed_time":1.148326933,"remaining_time":0.552898153},
{"learn":[3.558593054],"iteration":675,"passed_time":1.150625501,"remaining_time":0.5514832281},
{"learn":[3.555647008],"iteration":676,"passed_time":1.153283823,"remaining_time":0.5502373338},
{"learn":[3.553100059],"iteration":677,"passed_time":1.155670545,"remaining_time":0.5488582823},
{"learn":[3.55085578],"iteration":678,"passed_time":1.1575411,"remaining_time":0.5472322433},
{"learn":[3.550737965],"iteration":679,"passed_time":1.15894754,"remaining_time":0.5453870777},
{"learn":[3.549408772],"iteration":680,"passed_time":1.160654146,"remaining_time":0.5436838069},
{"learn":[3.547390589],"iteration":681,"passed_time":1.162617951,"remaining_time":0.5421004523},
{"learn":[3.54723575],"iteration":682,"passed_time":1.164214392,"remaining_time":0.5403454791},
{"learn":[3.543988891],"iteration":683,"passed_time":1.167422808,"remaining_time":0.5393356833},
{"learn":[3.543868508],"iteration":684,"passed_time":1.169605861,"remaining_time":0.5378479508},
{"learn":[3.542752124],"iteration":685,"passed_time":1.171885408,"remaining_time":0.5364023589},
{"learn":[3.541334315],"iteration":686,"passed_time":1.173654955,"remaining_time":0.5347219808},
{"learn":[3.540208266],"iteration":687,"passed_time":1.175313069,"remaining_time":0.5329908102},
{"learn":[3.537730983],"iteration":688,"passed_time":1.176803747,"remaining_time":0.5311842746},
{"learn":[3.53419867],"iteration":689,"passed_time":1.17846925,"remaining_time":0.5294571992},
{"learn":[3.532628335],"iteration":690,"passed_time":1.184518951,"remaining_time":0.5296908188},
{"learn":[3.532204987],"iteration":691,"passed_time":1.186299261,"remaining_time":0.5280060297},
{"learn":[3.530618147],"iteration":692,"passed_time":1.187986039,"remaining_time":0.5262795295},
{"learn":[3.528909306],"iteration":693,"passed_time":1.189591158,"remaining_time":0.5245171389},
{"learn":[3.526700678],"iteration":694,"passed_time":1.19141162,"remaining_time":0.5228497036},
{"learn":[3.526439574],"iteration":695,"passed_time":1.193001827,"remaining_time":0.5210812576},
{"learn":[3.525784216],"iteration":696,"passed_time":1.194296151,"remaining_time":0.519184697},
{"learn":[3.524112693],"iteration":697,"passed_time":1.196807744,"remaining_time":0.5178165311},
{"learn":[3.522813541],"iteration":698,"passed_time":1.198368431,"remaining_time":0.5160356189},
{"learn":[3.519148203],"iteration":699,"passed_time":1.199946262,"remaining_time":0.5142626839},
{"learn":[3.517236747],"iteration":700,"passed_time":1.20180583,"remaining_time":0.5126104753},
{"learn":[3.515603888],"iteration":701,"passed_time":1.203533085,"remaining_time":0.5109015089},
{"learn":[3.51263524],"iteration":702,"passed_time":1.204995829,"remaining_time":0.5090807414},
{"learn":[3.51123442],"iteration":703,"passed_time":1.206650859,"remaining_time":0.5073418383},
{"learn":[3.50828027],"iteration":704,"passed_time":1.208270338,"remaining_time":0.5055882973},
{"learn":[3.508265537],"iteration":705,"passed_time":1.209197306,"remaining_time":0.5035467535},
{"learn":[3.506774876],"iteration":706,"passed_time":1.211535058,"remaining_time":0.5020930297},
{"learn":[3.50552068],"iteration":707,"passed_time":1.215229765,"remaining_time":0.5011964567},
{"learn":[3.501973993],"iteration":708,"passed_time":1.216936176,"remaining_time":0.4994759199},
{"learn":[3.498880354],"iteration":709,"passed_time":1.218489887,"remaining_time":0.4976930525},
{"learn":[3.497370959],"iteration":710,"passed_time":1.219987548,"remaining_time":0.4958880471},
{"learn":[3.496050455],"iteration":711,"passed_time":1.221473121,"remaining_time":0.4940790154},
{"learn":[3.495630067],"iteration":712,"passed_time":1.222975942,"remaining_time":0.4922778337},
{"learn":[3.49550669],"iteration":713,"passed_time":1.224513351,"remaining_time":0.4904913422},
{"learn":[3.493652375],"iteration":714,"passed_time":1.227308615,"remaining_time":0.4892069306},
{"learn":[3.491915684],"iteration":715,"passed_time":1.229261564,"remaining_time":0.4875841958},
{"learn":[3.490303956],"iteration":716,"passed_time":1.230614205,"remaining_time":0.4857235982},
{"learn":[3.488363853],"iteration":717,"passed_time":1.232285189,"remaining_time":0.4839894474},
{"learn":[3.485483936],"iteration":718,"passed_time":1.233893311,"remaining_time":0.4822309045},
{"learn":[3.483763466],"iteration":719,"passed_time":1.235802342,"remaining_time":0.4805897998},
{"learn":[3.481642352],"iteration":720,"passed_time":1.237607874,"remaining_time":0.4789079013},
{"learn":[3.479826119],"iteration":721,"passed_time":1.239300942,"remaining_time":0.477182357},
{"learn":[3.478588728],"iteration":722,"passed_time":1.244804342,"remaining_time":0.4769167396},
{"learn":[3.475390887],"iteration":723,"passed_time":1.246586633,"remaining_time":0.4752181088},
{"learn":[3.472636852],"iteration":724,"passed_time":1.248129595,"remaining_time":0.4734284672},
{"learn":[3.47061883],"iteration":725,"passed_time":1.249884036,"remaining_time":0.4717193194},
{"learn":[3.46953149],"iteration":726,"passed_time":1.251527777,"remaining_time":0.4699684776},
{"learn":[3.467217162],"iteration":727,"passed_time":1.253346718,"remaining_time":0.468283389},
{"learn":[3.465686216],"iteration":728,"passed_time":1.255024419,"remaining_time":0.4665454286},
{"learn":[3.462631216],"iteration":729,"passed_time":1.257033931,"remaining_time":0.4649303581},
{"learn":[3.461451053],"iteration":730,"passed_time":1.258665773,"remaining_time":0.4631752298},
{"learn":[3.458950469],"iteration":731,"passed_time":1.260389466,"remaining_time":0.461454067},
{"learn":[3.458072145],"iteration":732,"passed_time":1.262548094,"remaining_time":0.459891325},
{"learn":[3.454364268],"iteration":733,"passed_time":1.264831335,"remaining_time":0.4583721188},
{"learn":[3.453243406],"iteration":734,"passed_time":1.266558341,"remaining_time":0.4566502862},
{"learn":[3.453017963],"iteration":735,"passed_time":1.268438925,"remaining_time":0.4549835274},
{"learn":[3.45201581],"iteration":736,"passed_time":1.270511584,"remaining_time":0.4533847308},
{"learn":[3.449510107],"iteration":737,"passed_time":1.276253842,"remaining_time":0.4530874074},
{"learn":[3.447189189],"iteration":738,"passed_time":1.27813219,"remaining_time":0.4514106921},
{"learn":[3.446423605],"iteration":739,"passed_time":1.27966432,"remaining_time":0.449611788},
{"learn":[3.445531987],"iteration":740,"passed_time":1.281343517,"remaining_time":0.447865008},
{"learn":[3.445328199],"iteration":741,"passed_time":1.282767617,"remaining_time":0.4460297106},
{"learn":[3.443327544],"iteration":742,"passed_time":1.28432551,"remaining_time":0.4442417981},
{"learn":[3.441475798],"iteration":743,"passed_time":1.28624341,"remaining_time":0.4425783778},
{"learn":[3.439046501],"iteration":744,"passed_time":1.287921667,"remaining_time":0.4408322484},
{"learn":[3.435899469],"iteration":745,"passed_time":1.289374775,"remaining_time":0.4390096417},
{"learn":[3.433988352],"iteration":746,"passed_time":1.290869002,"remaining_time":0.4372019511},
{"learn":[3.433413263],"iteration":747,"passed_time":1.292339932,"remaining_time":0.4353872499},
{"learn":[3.429944699],"iteration":748,"passed_time":1.293659941,"remaining_time":0.4335228908},
{"learn":[3.429291634],"iteration":749,"passed_time":1.295133565,"remaining_time":0.4317111884},
{"learn":[3.429175603],"iteration":750,"passed_time":1.29632884,"remaining_time":0.4298080973},
{"learn":[3.428780323],"iteration":751,"passed_time":1.297570012,"remaining_time":0.4279220253},
{"learn":[3.423893341],"iteration":752,"passed_time":1.298901543,"remaining_time":0.4260673056},
{"learn":[3.421024316],"iteration":753,"passed_time":1.300247461,"remaining_time":0.4242186678},
{"learn":[3.420969872],"iteration":754,"passed_time":1.302263611,"remaining_time":0.4225888539},
{"learn":[3.419544785],"iteration":755,"passed_time":1.304333361,"remaining_time":0.4209753176},
{"learn":[3.417057977],"iteration":756,"passed_time":1.305990939,"remaining_time":0.4192282672},
{"learn":[3.415160245],"iteration":757,"passed_time":1.307521947,"remaining_time":0.4174410439},
{"learn":[3.412854597],"iteration":758,"passed_time":1.309062624,"remaining_time":0.4156575657},
{"learn":[3.410926347],"iteration":759,"passed_time":1.310399158,"remaining_time":0.4138102605},
{"learn":[3.408963843],"iteration":760,"passed_time":1.311949516,"remaining_time":0.4120314512},
{"learn":[3.407629634],"iteration":761,"passed_time":1.313369625,"remaining_time":0.4102125601},
{"learn":[3.404384724],"iteration":762,"passed_time":1.314644767,"remaining_time":0.4083496851},
{"learn":[3.403041656],"iteration":763,"passed_time":1.315864938,"remaining_time":0.4064713683},
{"learn":[3.401101731],"iteration":764,"passed_time":1.317740753,"remaining_time":0.404796179},
{"learn":[3.400890668],"iteration":765,"passed_time":1.319286053,"remaining_time":0.4030194993},
{"learn":[3.399289941],"iteration":766,"passed_time":1.320664288,"remaining_time":0.4011926717},
{"learn":[3.399202366],"iteration":767,"passed_time":1.322177642,"remaining_time":0.3994078294},
{"learn":[3.397447845],"iteration":768,"passed_time":1.323729668,"remaining_time":0.39763531},
{"learn":[3.394655341],"iteration":769,"passed_time":1.325283179,"remaining_time":0.3958638068},
{"learn":[3.393228229],"iteration":770,"passed_time":1.32650298,"remaining_time":0.3939937515},
{"learn":[3.389691197],"iteration":771,"passed_time":1.327690371,"remaining_time":0.3921158091},
{"learn":[3.389626772],"iteration":772,"passed_time":1.328825286,"remaining_time":0.3902242431},
{"learn":[3.388480222],"iteration":773,"passed_time":1.330145687,"remaining_time":0.3883887924},
{"learn":[3.388215066],"iteration":774,"passed_time":1.331987764,"remaining_time":0.386706125},
{"learn":[3.386324358],"iteration":775,"passed_time":1.336045076,"remaining_time":0.3856624962},
{"learn":[3.383913061],"iteration":776,"passed_time":1.337701343,"remaining_time":0.383922007},
{"learn":[3.382839768],"iteration":777,"passed_time":1.3391363,"remaining_time":0.3821185842},
{"learn":[3.381961844],"iteration":778,"passed_time":1.340578249,"remaining_time":0.3803180913},
{"learn":[3.381521703],"iteration":779,"passed_time":1.342055721,"remaining_time":0.3785285366},
{"learn":[3.380918963],"iteration":780,"passed_time":1.34343142,"remaining_time":0.3767112433},
{"learn":[3.377139006],"iteration":781,"passed_time":1.344783205,"remaining_time":0.3748884126},
{"learn":[3.376004372],"iteration":782,"passed_time":1.346104223,"remaining_time":0.3730582584},
{"learn":[3.373826468],"iteration":783,"passed_time":1.348132464,"remaining_time":0.3714242504},
{"learn":[3.373546786],"iteration":784,"passed_time":1.349703866,"remaining_time":0.3696641161},
{"learn":[3.372109181],"iteration":785,"passed_time":1.351062519,"remaining_time":0.3678465383},
{"learn":[3.370764924],"iteration":786,"passed_time":1.352668799,"remaining_time":0.3660971464},
{"learn":[3.367833107],"iteration":787,"passed_time":1.354194556,"remaining_time":0.3643264542},
{"learn":[3.36450404],"iteration":788,"passed_time":1.355515554,"remaining_time":0.3625016247},
{"learn":[3.361794558],"iteration":789,"passed_time":1.356681871,"remaining_time":0.360636953},
{"learn":[3.356880529],"iteration":790,"passed_time":1.357917904,"remaining_time":0.3587924677},
{"learn":[3.353843509],"iteration":791,"passed_time":1.35919835,"remaining_time":0.3569611828},
{"learn":[3.353640253],"iteration":792,"passed_time":1.360440549,"remaining_time":0.3551213036},
{"learn":[3.353055088],"iteration":793,"passed_time":1.363055001,"remaining_time":0.3536389549},
{"learn":[3.351415617],"iteration":794,"passed_time":1.366205327,"remaining_time":0.3522919397},
{"learn":[3.349169061],"iteration":795,"passed_time":1.36771006,"remaining_time":0.3505186587},
{"learn":[3.346211014],"iteration":796,"passed_time":1.368972396,"remaining_time":0.3486843117},
{"learn":[3.344560452],"iteration":797,"passed_time":1.370427075,"remaining_time":0.3469000868},
{"learn":[3.344445461],"iteration":798,"passed_time":1.371639636,"remaining_time":0.3450557782},
{"learn":[3.342608898],"iteration":799,"passed_time":1.372777799,"remaining_time":0.3431944498},
{"learn":[3.339572899],"iteration":800,"passed_time":1.37405564,"remaining_time":0.3413696284},
{"learn":[3.339309302],"iteration":801,"passed_time":1.375238683,"remaining_time":0.3395227671},
{"learn":[3.33698088],"iteration":802,"passed_time":1.376971427,"remaining_time":0.3378124173},
{"learn":[3.334746342],"iteration":803,"passed_time":1.378764216,"remaining_time":0.3361166497},
{"learn":[3.332048511],"iteration":804,"passed_time":1.38062989,"remaining_time":0.3344382962},
{"learn":[3.331932544],"iteration":805,"passed_time":1.381980265,"remaining_time":0.3326354484},
{"learn":[3.330541133],"iteration":806,"passed_time":1.38330978,"remaining_time":0.3308287331},
{"learn":[3.329124989],"iteration":807,"passed_time":1.384398449,"remaining_time":0.3289659682},
{"learn":[3.32583918],"iteration":808,"passed_time":1.385628377,"remaining_time":0.3271384671},
{"learn":[3.325287299],"iteration":809,"passed_time":1.386761324,"remaining_time":0.3252896933},
{"learn":[3.322745162],"iteration":810,"passed_time":1.388007035,"remaining_time":0.3234689637},
{"learn":[3.319733662],"iteration":811,"passed_time":1.389517791,"remaining_time":0.3217110156},
{"learn":[3.318080007],"iteration":812,"passed_time":1.390883718,"remaining_time":0.3199203632},
{"learn":[3.317179538],"iteration":813,"passed_time":1.392568157,"remaining_time":0.3182035347},
{"learn":[3.315685949],"iteration":814,"passed_time":1.394547251,"remaining_time":0.3165536705},
{"learn":[3.314944576],"iteration":815,"passed_time":1.396136648,"remaining_time":0.3148151265},
{"learn":[3.312369052],"iteration":816,"passed_time":1.397572519,"remaining_time":0.3130425593},
{"learn":[3.312321621],"iteration":817,"passed_time":1.398650646,"remaining_time":0.3111912194},
{"learn":[3.309465776],"iteration":818,"passed_time":1.399923957,"remaining_time":0.3093849038},
{"learn":[3.308307377],"iteration":819,"passed_time":1.401112736,"remaining_time":0.3075613323},
{"learn":[3.308076804],"iteration":820,"passed_time":1.402263917,"remaining_time":0.3057311097},
{"learn":[3.305643326],"iteration":821,"passed_time":1.403799884,"remaining_time":0.303985863},
{"learn":[3.304154814],"iteration":822,"passed_time":1.405307164,"remaining_time":0.3022349552},
{"learn":[3.303076321],"iteration":823,"passed_time":1.407493572,"remaining_time":0.3006296949},
{"learn":[3.301746372],"iteration":824,"passed_time":1.409600141,"remaining_time":0.2990060905},
{"learn":[3.301345455],"iteration":825,"passed_time":1.410960688,"remaining_time":0.2972241642},
{"learn":[3.299181039],"iteration":826,"passed_time":1.412221336,"remaining_time":0.2954223592},
{"learn":[3.297989357],"iteration":827,"passed_time":1.413612194,"remaining_time":0.2936489098},
{"learn":[3.294775182],"iteration":828,"passed_time":1.414809995,"remaining_time":0.2918365612},
{"learn":[3.293840636],"iteration":829,"passed_time":1.416084527,"remaining_time":0.2900414092},
{"learn":[3.289279397],"iteration":830,"passed_time":1.417343305,"remaining_time":0.2882443063},
{"learn":[3.286204979],"iteration":831,"passed_time":1.418703207,"remaining_time":0.2864689168},
{"learn":[3.284833593],"iteration":832,"passed_time":1.420224374,"remaining_time":0.2847268554},
{"learn":[3.283519914],"iteration":833,"passed_time":1.421481912,"remaining_time":0.2829328505},
{"learn":[3.282853026],"iteration":834,"passed_time":1.424569811,"remaining_time":0.281501819},
{"learn":[3.281944673],"iteration":835,"passed_time":1.426174136,"remaining_time":0.2797757874},
{"learn":[3.279764865],"iteration":836,"passed_time":1.427556288,"remaining_time":0.2780067802},
{"learn":[3.277468839],"iteration":837,"passed_time":1.42895401,"remaining_time":0.276241706},
{"learn":[3.277124974],"iteration":838,"passed_time":1.431428549,"remaining_time":0.2746841435},
{"learn":[3.275636037],"iteration":839,"passed_time":1.432837337,"remaining_time":0.2729213975},
{"learn":[3.274413635],"iteration":840,"passed_time":1.434222731,"remaining_time":0.2711550704},
{"learn":[3.272636087],"iteration":841,"passed_time":1.435778488,"remaining_time":0.2694216165},
{"learn":[3.269644466],"iteration":842,"passed_time":1.437751995,"remaining_time":0.2677663858},
{"learn":[3.26852083],"iteration":843,"passed_time":1.43954563,"remaining_time":0.2660771543},
{"learn":[3.267820927],"iteration":844,"passed_time":1.440740804,"remaining_time":0.2642778989},
{"learn":[3.267331099],"iteration":845,"passed_time":1.442178319,"remaining_time":0.2625241858},
{"learn":[3.267231014],"iteration":846,"passed_time":1.443627114,"remaining_time":0.2607732567},
{"learn":[3.267158695],"iteration":847,"passed_time":1.445120261,"remaining_time":0.2590309902},
{"learn":[3.264718705],"iteration":848,"passed_time":1.446288777,"remaining_time":0.2572315728},
{"learn":[3.261678512],"iteration":849,"passed_time":1.447511007,"remaining_time":0.2554431189},
{"learn":[3.261368381],"iteration":850,"passed_time":1.448687118,"remaining_time":0.2536479208},
{"learn":[3.260128799],"iteration":851,"passed_time":1.449915844,"remaining_time":0.2518633156},
{"learn":[3.258972952],"iteration":852,"passed_time":1.451181175,"remaining_time":0.2500863221},
{"learn":[3.258724846],"iteration":853,"passed_time":1.452885397,"remaining_time":0.2483855597},
{"learn":[3.25686724],"iteration":854,"passed_time":1.455497703,"remaining_time":0.2468387918},
{"learn":[3.255750259],"iteration":855,"passed_time":1.456795234,"remaining_time":0.2450683571},
{"learn":[3.254915866],"iteration":856,"passed_time":1.457988116,"remaining_time":0.2432815643},
{"learn":[3.254348625],"iteration":857,"passed_time":1.459392889,"remaining_time":0.2415312241},
{"learn":[3.253408514],"iteration":858,"passed_time":1.460547542,"remaining_time":0.2397406327},
{"learn":[3.253291714],"iteration":859,"passed_time":1.461629111,"remaining_time":0.2379396227},
{"learn":[3.250186342],"iteration":860,"passed_time":1.462826306,"remaining_time":0.2361589506},
{"learn":[3.249141318],"iteration":861,"passed_time":1.463969671,"remaining_time":0.2343710146},
{"learn":[3.246300388],"iteration":862,"passed_time":1.465696282,"remaining_time":0.2326771619},
{"learn":[3.245205135],"iteration":863,"passed_time":1.467458085,"remaining_time":0.2309887727},
{"learn":[3.244403535],"iteration":864,"passed_time":1.468863121,"remaining_time":0.2292445333},
{"learn":[3.244211781],"iteration":865,"passed_time":1.47033619,"remaining_time":0.2275116044},
{"learn":[3.242286347],"iteration":866,"passed_time":1.471818281,"remaining_time":0.2257806591},
{"learn":[3.239606746],"iteration":867,"passed_time":1.473458947,"remaining_time":0.224074402},
{"learn":[3.236773361],"iteration":868,"passed_time":1.474749587,"remaining_time":0.2223155304},
{"learn":[3.234552446],"iteration":869,"passed_time":1.476129405,"remaining_time":0.2205710605},
{"learn":[3.233724647],"iteration":870,"passed_time":1.477510776,"remaining_time":0.2188276579},
{"learn":[3.230851485],"iteration":871,"passed_time":1.479083427,"remaining_time":0.2171131636},
{"learn":[3.227728941],"iteration":872,"passed_time":1.482990113,"remaining_time":0.2157385388},
{"learn":[3.225787575],"iteration":873,"passed_time":1.484484751,"remaining_time":0.2140103874},
{"learn":[3.222797487],"iteration":874,"passed_time":1.485765233,"remaining_time":0.2122521761},
{"learn":[3.22137014],"iteration":875,"passed_time":1.487093299,"remaining_time":0.2105017911},
{"learn":[3.219701963],"iteration":876,"passed_time":1.488575829,"remaining_time":0.208774033},
{"learn":[3.21783327],"iteration":877,"passed_time":1.489949677,"remaining_time":0.2070317319},
{"learn":[3.217713355],"iteration":878,"passed_time":1.491433993,"remaining_time":0.2053054758},
{"learn":[3.217666091],"iteration":879,"passed_time":1.49285911,"remaining_time":0.2035716969},
{"learn":[3.214962005],"iteration":880,"passed_time":1.494469894,"remaining_time":0.2018636974},
{"learn":[3.214081828],"iteration":881,"passed_time":1.496308133,"remaining_time":0.2001863489},
{"learn":[3.213358337],"iteration":882,"passed_time":1.498450729,"remaining_time":0.1985489641},
{"learn":[3.210850401],"iteration":883,"passed_time":1.500025171,"remaining_time":0.1968358821},
{"learn":[3.207810328],"iteration":884,"passed_time":1.501765903,"remaining_time":0.1951447219},
{"learn":[3.204935073],"iteration":885,"passed_time":1.503239316,"remaining_time":0.1934190542},
{"learn":[3.20280198],"iteration":886,"passed_time":1.504860359,"remaining_time":0.1917127627},
{"learn":[3.200663495],"iteration":887,"passed_time":1.506484968,"remaining_time":0.1900071131},
{"learn":[3.197301669],"iteration":888,"passed_time":1.507808601,"remaining_time":0.188264066},
{"learn":[3.195666943],"iteration":889,"passed_time":1.50926193,"remaining_time":0.1865379914},
{"learn":[3.193886506],"iteration":890,"passed_time":1.510846153,"remaining_time":0.1848285418},
{"learn":[3.190601248],"iteration":891,"passed_time":1.514368708,"remaining_time":0.1833540588},
{"learn":[3.188983797],"iteration":892,"passed_time":1.515827429,"remaining_time":0.1816276986},
{"learn":[3.187365749],"iteration":893,"passed_time":1.517141141,"remaining_time":0.1798847438},
{"learn":[3.186160771],"iteration":894,"passed_time":1.518448732,"remaining_time":0.17814203},
{"learn":[3.185358981],"iteration":895,"passed_time":1.519861349,"remaining_time":0.176412478},
{"learn":[3.183832164],"iteration":896,"passed_time":1.521286305,"remaining_time":0.1746850495},
{"learn":[3.183106966],"iteration":897,"passed_time":1.522725683,"remaining_time":0.1729599328},
{"learn":[3.182838152],"iteration":898,"passed_time":1.52458195,"remaining_time":0.1712822881},
{"learn":[3.180835453],"iteration":899,"passed_time":1.52687514,"remaining_time":0.1696527934},
{"learn":[3.179957348],"iteration":900,"passed_time":1.528769807,"remaining_time":0.1679780365},
{"learn":[3.179752966],"iteration":901,"passed_time":1.53035339,"remaining_time":0.1662689936},
{"learn":[3.178851983],"iteration":902,"passed_time":1.53183198,"remaining_time":0.1645489503},
{"learn":[3.176748586],"iteration":903,"passed_time":1.533567009,"remaining_time":0.1628566735},
{"learn":[3.172960988],"iteration":904,"passed_time":1.535110484,"remaining_time":0.1611441945},
{"learn":[3.172794225],"iteration":905,"passed_time":1.536423045,"remaining_time":0.1594081305},
{"learn":[3.169996507],"iteration":906,"passed_time":1.538183036,"remaining_time":0.157718878},
{"learn":[3.16813015],"iteration":907,"passed_time":1.540872722,"remaining_time":0.1561236679},
{"learn":[3.166920871],"iteration":908,"passed_time":1.543227577,"remaining_time":0.1544925297},
{"learn":[3.16531606],"iteration":909,"passed_time":1.544710015,"remaining_time":0.152773518},
{"learn":[3.162035247],"iteration":910,"passed_time":1.546451931,"remaining_time":0.1510803752},
{"learn":[3.16189467],"iteration":911,"passed_time":1.548440056,"remaining_time":0.1494108826},
{"learn":[3.161008416],"iteration":912,"passed_time":1.550361244,"remaining_time":0.1477343135},
{"learn":[3.160560787],"iteration":913,"passed_time":1.551971476,"remaining_time":0.1460279507},
{"learn":[3.160416261],"iteration":914,"passed_time":1.553276612,"remaining_time":0.1442934558},
{"learn":[3.15844291],"iteration":915,"passed_time":1.555481896,"remaining_time":0.1426424447},
{"learn":[3.155040501],"iteration":916,"passed_time":1.557514267,"remaining_time":0.1409745738},
{"learn":[3.154937548],"iteration":917,"passed_time":1.558937684,"remaining_time":0.1392515143},
{"learn":[3.153721161],"iteration":918,"passed_time":1.56064174,"remaining_time":0.1375538422},
{"learn":[3.153170511],"iteration":919,"passed_time":1.56202724,"remaining_time":0.1358284556},
{"learn":[3.153113601],"iteration":920,"passed_time":1.563626759,"remaining_time":0.134122165},
{"learn":[3.150607379],"iteration":921,"passed_time":1.565188763,"remaining_time":0.1324129323},
{"learn":[3.148408359],"iteration":922,"passed_time":1.566768884,"remaining_time":0.1307055299},
{"learn":[3.147495728],"iteration":923,"passed_time":1.568717607,"remaining_time":0.1290287209},
{"learn":[3.146946235],"iteration":924,"passed_time":1.57547507,"remaining_time":0.1277412219},
{"learn":[3.14472738],"iteration":925,"passed_time":1.577963924,"remaining_time":0.1261007888},
{"learn":[3.144469477],"iteration":926,"passed_time":1.580306396,"remaining_time":0.1244469978},
{"learn":[3.142975516],"iteration":927,"passed_time":1.582156749,"remaining_time":0.1227535409},
{"learn":[3.14079113],"iteration":928,"passed_time":1.584055257,"remaining_time":0.1210634265},
{"learn":[3.138173032],"iteration":929,"passed_time":1.586476388,"remaining_time":0.1194122012},
{"learn":[3.136352813],"iteration":930,"passed_time":1.588336432,"remaining_time":0.1177177377},
{"learn":[3.133735004],"iteration":931,"passed_time":1.589811294,"remaining_time":0.1159948155},
{"learn":[3.1319496],"iteration":932,"passed_time":1.591684295,"remaining_time":0.1143010158},
{"learn":[3.129865343],"iteration":933,"passed_time":1.593886613,"remaining_time":0.1126301033},
{"learn":[3.129830206],"iteration":934,"passed_time":1.596063839,"remaining_time":0.1109563096},
{"learn":[3.126676562],"iteration":935,"passed_time":1.598206464,"remaining_time":0.1092790745},
{"learn":[3.12645665],"iteration":936,"passed_time":1.600541413,"remaining_time":0.107613777},
{"learn":[3.126378007],"iteration":937,"passed_time":1.60398556,"remaining_time":0.1060203675},
{"learn":[3.124621914],"iteration":938,"passed_time":1.606827564,"remaining_time":0.1043838993},
{"learn":[3.123379018],"iteration":939,"passed_time":1.608848846,"remaining_time":0.1026924795},
{"learn":[3.123332451],"iteration":940,"passed_time":1.610813931,"remaining_time":0.1009968352},
{"learn":[3.122432444],"iteration":941,"passed_time":1.613118781,"remaining_time":0.09932153851},
{"learn":[3.121889006],"iteration":942,"passed_time":1.615982257,"remaining_time":0.09767867303},
{"learn":[3.121070914],"iteration":943,"passed_time":1.618822057,"remaining_time":0.09603181695},
{"learn":[3.118444705],"iteration":944,"passed_time":1.62052383,"remaining_time":0.09431620177},
{"learn":[3.116820458],"iteration":945,"passed_time":1.622756423,"remaining_time":0.09263091633},
{"learn":[3.114971041],"iteration":946,"passed_time":1.624427212,"remaining_time":0.09091303297},
{"learn":[3.114685138],"iteration":947,"passed_time":1.626287561,"remaining_time":0.08920564682},
{"learn":[3.113399363],"iteration":948,"passed_time":1.628110083,"remaining_time":0.08749590542},
{"learn":[3.110575399],"iteration":949,"passed_time":1.63021693,"remaining_time":0.08580089107},
{"learn":[3.110466553],"iteration":950,"passed_time":1.632001698,"remaining_time":0.08408841558},
{"learn":[3.108691641],"iteration":951,"passed_time":1.635177481,"remaining_time":0.08244592342},
{"learn":[3.107898017],"iteration":952,"passed_time":1.653892424,"remaining_time":0.08156657287},
{"learn":[3.105551729],"iteration":953,"passed_time":1.657124816,"remaining_time":0.07990329301},
{"learn":[3.104824945],"iteration":954,"passed_time":1.659415286,"remaining_time":0.07819234331},
{"learn":[3.103186704],"iteration":955,"passed_time":1.661682888,"remaining_time":0.07647912874},
{"learn":[3.102330655],"iteration":956,"passed_time":1.665136718,"remaining_time":0.07481805523},
{"learn":[3.102291298],"iteration":957,"passed_time":1.667333357,"remaining_time":0.07309812211},
{"learn":[3.100363529],"iteration":958,"passed_time":1.669498881,"remaining_time":0.07137586459},
{"learn":[3.097871596],"iteration":959,"passed_time":1.671754995,"remaining_time":0.06965645812},
{"learn":[3.097372213],"iteration":960,"passed_time":1.673959407,"remaining_time":0.06793383651},
{"learn":[3.095981813],"iteration":961,"passed_time":1.676080097,"remaining_time":0.06620690614},
{"learn":[3.095347452],"iteration":962,"passed_time":1.682699552,"remaining_time":0.06465200771},
{"learn":[3.094728409],"iteration":963,"passed_time":1.684975956,"remaining_time":0.06292441328},
{"learn":[3.094118537],"iteration":964,"passed_time":1.687687138,"remaining_time":0.0612114506},
{"learn":[3.093793695],"iteration":965,"passed_time":1.689831813,"remaining_time":0.05947648203},
{"learn":[3.092581602],"iteration":966,"passed_time":1.692029498,"remaining_time":0.05774247511},
{"learn":[3.091694202],"iteration":967,"passed_time":1.694817301,"remaining_time":0.05602701821},
{"learn":[3.090298312],"iteration":968,"passed_time":1.698816027,"remaining_time":0.05434808754},
{"learn":[3.090020107],"iteration":969,"passed_time":1.700859097,"remaining_time":0.05260388959},
{"learn":[3.088949869],"iteration":970,"passed_time":1.702971905,"remaining_time":0.05086115886},
{"learn":[3.086700204],"iteration":971,"passed_time":1.705347056,"remaining_time":0.04912522383},
{"learn":[3.086584317],"iteration":972,"passed_time":1.707633531,"remaining_time":0.04738551421},
{"learn":[3.084850742],"iteration":973,"passed_time":1.70985208,"remaining_time":0.04564286867},
{"learn":[3.084239948],"iteration":974,"passed_time":1.713212261,"remaining_time":0.0439285195},
{"learn":[3.082561673],"iteration":975,"passed_time":1.717389866,"remaining_time":0.04223089833},
{"learn":[3.07991814],"iteration":976,"passed_time":1.720529023,"remaining_time":0.04050375387},
{"learn":[3.079350277],"iteration":977,"passed_time":1.723248233,"remaining_time":0.03876427518},
{"learn":[3.077637462],"iteration":978,"passed_time":1.725384709,"remaining_time":0.03701029509},
{"learn":[3.076733301],"iteration":979,"passed_time":1.727360947,"remaining_time":0.03525226422},
{"learn":[3.07594065],"iteration":980,"passed_time":1.729402472,"remaining_time":0.03349505298},
{"learn":[3.072594655],"iteration":981,"passed_time":1.731499627,"remaining_time":0.03173828236},
{"learn":[3.071977674],"iteration":982,"passed_time":1.734132277,"remaining_time":0.02999008008},
{"learn":[3.069532634],"iteration":983,"passed_time":1.748225094,"remaining_time":0.02842642429},
{"learn":[3.068870784],"iteration":984,"passed_time":1.750315214,"remaining_time":0.0266545464},
{"learn":[3.068801463],"iteration":985,"passed_time":1.752793484,"remaining_time":0.02488753426},
{"learn":[3.067433249],"iteration":986,"passed_time":1.755624992,"remaining_time":0.02312373344},
{"learn":[3.065611456],"iteration":987,"passed_time":1.757679346,"remaining_time":0.02134833214},
{"learn":[3.063039162],"iteration":988,"passed_time":1.75976091,"remaining_time":0.01957266937},
{"learn":[3.06177873],"iteration":989,"passed_time":1.761908411,"remaining_time":0.01779705465},
{"learn":[3.061689148],"iteration":990,"passed_time":1.76532842,"remaining_time":0.01603224599},
{"learn":[3.058984039],"iteration":991,"passed_time":1.766970479,"remaining_time":0.01424976193},
{"learn":[3.057492984],"iteration":992,"passed_time":1.76856887,"remaining_time":0.01246725286},
{"learn":[3.057290731],"iteration":993,"passed_time":1.772015075,"remaining_time":0.01069626806},
{"learn":[3.056068348],"iteration":994,"passed_time":1.773385894,"remaining_time":0.008911486904},
{"learn":[3.054987307],"iteration":995,"passed_time":1.774978702,"remaining_time":0.007128428524},
{"learn":[3.054200234],"iteration":996,"passed_time":1.776359342,"remaining_time":0.005345113365},
{"learn":[3.052732869],"iteration":997,"passed_time":1.777618195,"remaining_time":0.003562361112},
{"learn":[3.051787862],"iteration":998,"passed_time":1.779266795,"remaining_time":0.001781047843},
{"learn":[3.051366222],"iteration":999,"passed_time":1.780934469,"remaining_time":0}
]}